allCircuit.v
primitive mux (y, a, b, sel);
  output y;
  input a, b, sel;
  table
    // a  b  sel  :  y
       0  ?   0   :  0;
       1  ?   0   :  1;
       ?  0   1   :  0;
       ?  1   1   :  1;
  endtable
endprimitive

module allCircuit(a,b,c,d,e,f,g,h,i,in1,in2,in3,in4,in5,in6,t,n,r,k,m);

    input a,b,c,d,e,f,g,h,i,in1,in2,in3,in4,in5,in6;
    output t,k,m,n,r;

    wire j,k3,l,m3,m1,n3,o,p,q,r3,s;

    not(j,a);
    nand(k,c,d);
    mux(k3,k,in1,in2);
    xnor(l,e,f);
    xor(m,g,h,i);
    or(m1,m,in3);
    and(m3,m1,in4);
    and(n,j,b);
    or(n3,n,in5);
    or(o,b,m3);
    nand(p,l,m3);
    and(q,n3,o,p);
    and(r,k3,o,p);
    and(r3,r,in6);
    xor(s,q,r3);
    or(t,n3,s,r3);

endmodule

allCircuitTest.v
`timescale 1ps/1ps
module test();

    reg a,b,c,d,e,f,g,h,i,in1,in2,in3,in4,in5,in6;
    wire t,n,k,r,m;

    allCircuit uut(.a(a),.b(b),.c(c),.d(d),.e(e),.f(f),.g(g),.h(h),.i(i),.in1(in1),.in2(in2),.in3(in3),.in4(in4),.in5(in5),.in6(in6),.t(t),.n(n),.r(r),.k(k),.m(m));

    initial begin
		$dumpfile("allCircuit.vcd");
     	$dumpvars(0,test);

		// Initialize Inputs
		a = 1'b0;
		b = 1'b0;
        c = 1'b0;
        d = 1'b0;
        e = 1'b0;
        f = 1'b0;
        g = 1'b0;
        h = 1'b0;
        i = 1'b0;

        //Change these for control pin inputs
        in1 = 1'b1;
        in2 = 1'b1;
        in3 = 1'b1;
        in4 = 1'b1;
        in5 = 1'b0;
        in6 = 1'b0;

		#2565 $finish;//global reset
	end

    //Generating all possible 64 combinations
	always #5 a=~a;
	always #10 b=~b;
    always #20 c=~c;
    always #40 d=~d;
    always #80 e=~e;
    always #160 f=~f;
    always #320 g=~g;
    always #640 h=~h;
    always #1280 i=~i;

    //printing values for each new test vector
	always #5
    $display("t=%b n=%b r=%b k=%b m=%b",t,n,r,k,m);

endmodule

Executables/allCircuit.vcd
$date
	Wed Oct 27 01:59:44 2021
$end
$version
	Icarus Verilog
$end
$timescale
	1ps
$end
$scope module test $end
$var wire 1 ! t $end
$var wire 1 " r $end
$var wire 1 # n $end
$var wire 1 $ m $end
$var wire 1 % k $end
$var reg 1 & a $end
$var reg 1 ' b $end
$var reg 1 ( c $end
$var reg 1 ) d $end
$var reg 1 * e $end
$var reg 1 + f $end
$var reg 1 , g $end
$var reg 1 - h $end
$var reg 1 . i $end
$var reg 1 / in1 $end
$var reg 1 0 in2 $end
$var reg 1 1 in3 $end
$var reg 1 2 in4 $end
$var reg 1 3 in5 $end
$var reg 1 4 in6 $end
$scope module uut $end
$var wire 1 & a $end
$var wire 1 ' b $end
$var wire 1 ( c $end
$var wire 1 ) d $end
$var wire 1 * e $end
$var wire 1 + f $end
$var wire 1 , g $end
$var wire 1 - h $end
$var wire 1 . i $end
$var wire 1 / in1 $end
$var wire 1 0 in2 $end
$var wire 1 1 in3 $end
$var wire 1 2 in4 $end
$var wire 1 3 in5 $end
$var wire 1 4 in6 $end
$var wire 1 5 j $end
$var wire 1 % k $end
$var wire 1 6 k3 $end
$var wire 1 7 l $end
$var wire 1 $ m $end
$var wire 1 8 m1 $end
$var wire 1 9 m3 $end
$var wire 1 # n $end
$var wire 1 : n3 $end
$var wire 1 ; o $end
$var wire 1 < p $end
$var wire 1 = q $end
$var wire 1 " r $end
$var wire 1 > r3 $end
$var wire 1 ? s $end
$var wire 1 ! t $end
$upscope $end
$upscope $end
$enddefinitions $end
#0
$dumpvars
0?
0>
0=
0<
1;
0:
19
18
17
16
15
04
03
12
11
10
1/
0.
0-
0,
0+
0*
0)
0(
0'
0&
1%
0$
0#
0"
0!
$end
#5
05
1&
#10
1!
1:
1#
15
0&
1'
#15
0!
0:
0#
05
1&
#20
15
0&
0'
1(
#25
05
1&
#30
1!
1:
1#
15
0&
1'
#35
0!
0:
0#
05
1&
#40
15
0&
0'
0(
1)
#45
05
1&
#50
1!
1:
1#
15
0&
1'
#55
0!
0:
0#
05
1&
#60
15
0%
0&
0'
1(
#65
05
1&
#70
1!
1:
1#
15
0&
1'
#75
0!
0:
0#
05
1&
#80
1"
1<
15
1%
07
0&
0'
0(
0)
1*
#85
05
1&
#90
1?
1=
1!
1:
1#
15
0&
1'
#95
0!
0?
0=
0:
0#
05
1&
#100
15
0&
0'
1(
#105
05
1&
#110
1?
1=
1!
1:
1#
15
0&
1'
#115
0!
0?
0=
0:
0#
05
1&
#120
15
0&
0'
0(
1)
#125
05
1&
#130
1?
1=
1!
1:
1#
15
0&
1'
#135
0!
0?
0=
0:
0#
05
1&
#140
15
0%
0&
0'
1(
#145
05
1&
#150
1?
1=
1!
1:
1#
15
0&
1'
#155
0!
0?
0=
0:
0#
05
1&
#160
15
1%
0&
0'
0(
0)
0*
1+
#165
05
1&
#170
1?
1=
1!
1:
1#
15
0&
1'
#175
0!
0?
0=
0:
0#
05
1&
#180
15
0&
0'
1(
#185
05
1&
#190
1?
1=
1!
1:
1#
15
0&
1'
#195
0!
0?
0=
0:
0#
05
1&
#200
15
0&
0'
0(
1)
#205
05
1&
#210
1?
1=
1!
1:
1#
15
0&
1'
#215
0!
0?
0=
0:
0#
05
1&
#220
15
0%
0&
0'
1(
#225
05
1&
#230
1?
1=
1!
1:
1#
15
0&
1'
#235
0!
0?
0=
0:
0#
05
1&
#240
0"
0<
15
1%
17
0&
0'
0(
0)
1*
#245
05
1&
#250
1!
1:
1#
15
0&
1'
#255
0!
0:
0#
05
1&
#260
15
0&
0'
1(
#265
05
1&
#270
1!
1:
1#
15
0&
1'
#275
0!
0:
0#
05
1&
#280
15
0&
0'
0(
1)
#285
05
1&
#290
1!
1:
1#
15
0&
1'
#295
0!
0:
0#
05
1&
#300
15
0%
0&
0'
1(
#305
05
1&
#310
1!
1:
1#
15
0&
1'
#315
0!
0:
0#
05
1&
#320
15
1%
1$
0&
0'
0(
0)
0*
0+
1,
#325
05
1&
#330
1!
1:
1#
15
0&
1'
#335
0!
0:
0#
05
1&
#340
15
0&
0'
1(
#345
05
1&
#350
1!
1:
1#
15
0&
1'
#355
0!
0:
0#
05
1&
#360
15
0&
0'
0(
1)
#365
05
1&
#370
1!
1:
1#
15
0&
1'
#375
0!
0:
0#
05
1&
#380
15
0%
0&
0'
1(
#385
05
1&
#390
1!
1:
1#
15
0&
1'
#395
0!
0:
0#
05
1&
#400
1"
1<
15
1%
07
0&
0'
0(
0)
1*
#405
05
1&
#410
1?
1=
1!
1:
1#
15
0&
1'
#415
0!
0?
0=
0:
0#
05
1&
#420
15
0&
0'
1(
#425
05
1&
#430
1?
1=
1!
1:
1#
15
0&
1'
#435
0!
0?
0=
0:
0#
05
1&
#440
15
0&
0'
0(
1)
#445
05
1&
#450
1?
1=
1!
1:
1#
15
0&
1'
#455
0!
0?
0=
0:
0#
05
1&
#460
15
0%
0&
0'
1(
#465
05
1&
#470
1?
1=
1!
1:
1#
15
0&
1'
#475
0!
0?
0=
0:
0#
05
1&
#480
15
1%
0&
0'
0(
0)
0*
1+
#485
05
1&
#490
1?
1=
1!
1:
1#
15
0&
1'
#495
0!
0?
0=
0:
0#
05
1&
#500
15
0&
0'
1(
#505
05
1&
#510
1?
1=
1!
1:
1#
15
0&
1'
#515
0!
0?
0=
0:
0#
05
1&
#520
15
0&
0'
0(
1)
#525
05
1&
#530
1?
1=
1!
1:
1#
15
0&
1'
#535
0!
0?
0=
0:
0#
05
1&
#540
15
0%
0&
0'
1(
#545
05
1&
#550
1?
1=
1!
1:
1#
15
0&
1'
#555
0!
0?
0=
0:
0#
05
1&
#560
0"
0<
15
1%
17
0&
0'
0(
0)
1*
#565
05
1&
#570
1!
1:
1#
15
0&
1'
#575
0!
0:
0#
05
1&
#580
15
0&
0'
1(
#585
05
1&
#590
1!
1:
1#
15
0&
1'
#595
0!
0:
0#
05
1&
#600
15
0&
0'
0(
1)
#605
05
1&
#610
1!
1:
1#
15
0&
1'
#615
0!
0:
0#
05
1&
#620
15
0%
0&
0'
1(
#625
05
1&
#630
1!
1:
1#
15
0&
1'
#635
0!
0:
0#
05
1&
#640
15
1%
0&
0'
0(
0)
0*
0+
0,
1-
#645
05
1&
#650
1!
1:
1#
15
0&
1'
#655
0!
0:
0#
05
1&
#660
15
0&
0'
1(
#665
05
1&
#670
1!
1:
1#
15
0&
1'
#675
0!
0:
0#
05
1&
#680
15
0&
0'
0(
1)
#685
05
1&
#690
1!
1:
1#
15
0&
1'
#695
0!
0:
0#
05
1&
#700
15
0%
0&
0'
1(
#705
05
1&
#710
1!
1:
1#
15
0&
1'
#715
0!
0:
0#
05
1&
#720
1"
1<
15
1%
07
0&
0'
0(
0)
1*
#725
05
1&
#730
1?
1=
1!
1:
1#
15
0&
1'
#735
0!
0?
0=
0:
0#
05
1&
#740
15
0&
0'
1(
#745
05
1&
#750
1?
1=
1!
1:
1#
15
0&
1'
#755
0!
0?
0=
0:
0#
05
1&
#760
15
0&
0'
0(
1)
#765
05
1&
#770
1?
1=
1!
1:
1#
15
0&
1'
#775
0!
0?
0=
0:
0#
05
1&
#780
15
0%
0&
0'
1(
#785
05
1&
#790
1?
1=
1!
1:
1#
15
0&
1'
#795
0!
0?
0=
0:
0#
05
1&
#800
15
1%
0&
0'
0(
0)
0*
1+
#805
05
1&
#810
1?
1=
1!
1:
1#
15
0&
1'
#815
0!
0?
0=
0:
0#
05
1&
#820
15
0&
0'
1(
#825
05
1&
#830
1?
1=
1!
1:
1#
15
0&
1'
#835
0!
0?
0=
0:
0#
05
1&
#840
15
0&
0'
0(
1)
#845
05
1&
#850
1?
1=
1!
1:
1#
15
0&
1'
#855
0!
0?
0=
0:
0#
05
1&
#860
15
0%
0&
0'
1(
#865
05
1&
#870
1?
1=
1!
1:
1#
15
0&
1'
#875
0!
0?
0=
0:
0#
05
1&
#880
0"
0<
15
1%
17
0&
0'
0(
0)
1*
#885
05
1&
#890
1!
1:
1#
15
0&
1'
#895
0!
0:
0#
05
1&
#900
15
0&
0'
1(
#905
05
1&
#910
1!
1:
1#
15
0&
1'
#915
0!
0:
0#
05
1&
#920
15
0&
0'
0(
1)
#925
05
1&
#930
1!
1:
1#
15
0&
1'
#935
0!
0:
0#
05
1&
#940
15
0%
0&
0'
1(
#945
05
1&
#950
1!
1:
1#
15
0&
1'
#955
0!
0:
0#
05
1&
#960
15
1%
0$
0&
0'
0(
0)
0*
0+
1,
#965
05
1&
#970
1!
1:
1#
15
0&
1'
#975
0!
0:
0#
05
1&
#980
15
0&
0'
1(
#985
05
1&
#990
1!
1:
1#
15
0&
1'
#995
0!
0:
0#
05
1&
#1000
15
0&
0'
0(
1)
#1005
05
1&
#1010
1!
1:
1#
15
0&
1'
#1015
0!
0:
0#
05
1&
#1020
15
0%
0&
0'
1(
#1025
05
1&
#1030
1!
1:
1#
15
0&
1'
#1035
0!
0:
0#
05
1&
#1040
1"
1<
15
1%
07
0&
0'
0(
0)
1*
#1045
05
1&
#1050
1?
1=
1!
1:
1#
15
0&
1'
#1055
0!
0?
0=
0:
0#
05
1&
#1060
15
0&
0'
1(
#1065
05
1&
#1070
1?
1=
1!
1:
1#
15
0&
1'
#1075
0!
0?
0=
0:
0#
05
1&
#1080
15
0&
0'
0(
1)
#1085
05
1&
#1090
1?
1=
1!
1:
1#
15
0&
1'
#1095
0!
0?
0=
0:
0#
05
1&
#1100
15
0%
0&
0'
1(
#1105
05
1&
#1110
1?
1=
1!
1:
1#
15
0&
1'
#1115
0!
0?
0=
0:
0#
05
1&
#1120
15
1%
0&
0'
0(
0)
0*
1+
#1125
05
1&
#1130
1?
1=
1!
1:
1#
15
0&
1'
#1135
0!
0?
0=
0:
0#
05
1&
#1140
15
0&
0'
1(
#1145
05
1&
#1150
1?
1=
1!
1:
1#
15
0&
1'
#1155
0!
0?
0=
0:
0#
05
1&
#1160
15
0&
0'
0(
1)
#1165
05
1&
#1170
1?
1=
1!
1:
1#
15
0&
1'
#1175
0!
0?
0=
0:
0#
05
1&
#1180
15
0%
0&
0'
1(
#1185
05
1&
#1190
1?
1=
1!
1:
1#
15
0&
1'
#1195
0!
0?
0=
0:
0#
05
1&
#1200
0"
0<
15
1%
17
0&
0'
0(
0)
1*
#1205
05
1&
#1210
1!
1:
1#
15
0&
1'
#1215
0!
0:
0#
05
1&
#1220
15
0&
0'
1(
#1225
05
1&
#1230
1!
1:
1#
15
0&
1'
#1235
0!
0:
0#
05
1&
#1240
15
0&
0'
0(
1)
#1245
05
1&
#1250
1!
1:
1#
15
0&
1'
#1255
0!
0:
0#
05
1&
#1260
15
0%
0&
0'
1(
#1265
05
1&
#1270
1!
1:
1#
15
0&
1'
#1275
0!
0:
0#
05
1&
#1280
15
1%
1$
0&
0'
0(
0)
0*
0+
0,
0-
1.
#1285
05
1&
#1290
1!
1:
1#
15
0&
1'
#1295
0!
0:
0#
05
1&
#1300
15
0&
0'
1(
#1305
05
1&
#1310
1!
1:
1#
15
0&
1'
#1315
0!
0:
0#
05
1&
#1320
15
0&
0'
0(
1)
#1325
05
1&
#1330
1!
1:
1#
15
0&
1'
#1335
0!
0:
0#
05
1&
#1340
15
0%
0&
0'
1(
#1345
05
1&
#1350
1!
1:
1#
15
0&
1'
#1355
0!
0:
0#
05
1&
#1360
1"
1<
15
1%
07
0&
0'
0(
0)
1*
#1365
05
1&
#1370
1?
1=
1!
1:
1#
15
0&
1'
#1375
0!
0?
0=
0:
0#
05
1&
#1380
15
0&
0'
1(
#1385
05
1&
#1390
1?
1=
1!
1:
1#
15
0&
1'
#1395
0!
0?
0=
0:
0#
05
1&
#1400
15
0&
0'
0(
1)
#1405
05
1&
#1410
1?
1=
1!
1:
1#
15
0&
1'
#1415
0!
0?
0=
0:
0#
05
1&
#1420
15
0%
0&
0'
1(
#1425
05
1&
#1430
1?
1=
1!
1:
1#
15
0&
1'
#1435
0!
0?
0=
0:
0#
05
1&
#1440
15
1%
0&
0'
0(
0)
0*
1+
#1445
05
1&
#1450
1?
1=
1!
1:
1#
15
0&
1'
#1455
0!
0?
0=
0:
0#
05
1&
#1460
15
0&
0'
1(
#1465
05
1&
#1470
1?
1=
1!
1:
1#
15
0&
1'
#1475
0!
0?
0=
0:
0#
05
1&
#1480
15
0&
0'
0(
1)
#1485
05
1&
#1490
1?
1=
1!
1:
1#
15
0&
1'
#1495
0!
0?
0=
0:
0#
05
1&
#1500
15
0%
0&
0'
1(
#1505
05
1&
#1510
1?
1=
1!
1:
1#
15
0&
1'
#1515
0!
0?
0=
0:
0#
05
1&
#1520
0"
0<
15
1%
17
0&
0'
0(
0)
1*
#1525
05
1&
#1530
1!
1:
1#
15
0&
1'
#1535
0!
0:
0#
05
1&
#1540
15
0&
0'
1(
#1545
05
1&
#1550
1!
1:
1#
15
0&
1'
#1555
0!
0:
0#
05
1&
#1560
15
0&
0'
0(
1)
#1565
05
1&
#1570
1!
1:
1#
15
0&
1'
#1575
0!
0:
0#
05
1&
#1580
15
0%
0&
0'
1(
#1585
05
1&
#1590
1!
1:
1#
15
0&
1'
#1595
0!
0:
0#
05
1&
#1600
15
1%
0$
0&
0'
0(
0)
0*
0+
1,
#1605
05
1&
#1610
1!
1:
1#
15
0&
1'
#1615
0!
0:
0#
05
1&
#1620
15
0&
0'
1(
#1625
05
1&
#1630
1!
1:
1#
15
0&
1'
#1635
0!
0:
0#
05
1&
#1640
15
0&
0'
0(
1)
#1645
05
1&
#1650
1!
1:
1#
15
0&
1'
#1655
0!
0:
0#
05
1&
#1660
15
0%
0&
0'
1(
#1665
05
1&
#1670
1!
1:
1#
15
0&
1'
#1675
0!
0:
0#
05
1&
#1680
1"
1<
15
1%
07
0&
0'
0(
0)
1*
#1685
05
1&
#1690
1?
1=
1!
1:
1#
15
0&
1'
#1695
0!
0?
0=
0:
0#
05
1&
#1700
15
0&
0'
1(
#1705
05
1&
#1710
1?
1=
1!
1:
1#
15
0&
1'
#1715
0!
0?
0=
0:
0#
05
1&
#1720
15
0&
0'
0(
1)
#1725
05
1&
#1730
1?
1=
1!
1:
1#
15
0&
1'
#1735
0!
0?
0=
0:
0#
05
1&
#1740
15
0%
0&
0'
1(
#1745
05
1&
#1750
1?
1=
1!
1:
1#
15
0&
1'
#1755
0!
0?
0=
0:
0#
05
1&
#1760
15
1%
0&
0'
0(
0)
0*
1+
#1765
05
1&
#1770
1?
1=
1!
1:
1#
15
0&
1'
#1775
0!
0?
0=
0:
0#
05
1&
#1780
15
0&
0'
1(
#1785
05
1&
#1790
1?
1=
1!
1:
1#
15
0&
1'
#1795
0!
0?
0=
0:
0#
05
1&
#1800
15
0&
0'
0(
1)
#1805
05
1&
#1810
1?
1=
1!
1:
1#
15
0&
1'
#1815
0!
0?
0=
0:
0#
05
1&
#1820
15
0%
0&
0'
1(
#1825
05
1&
#1830
1?
1=
1!
1:
1#
15
0&
1'
#1835
0!
0?
0=
0:
0#
05
1&
#1840
0"
0<
15
1%
17
0&
0'
0(
0)
1*
#1845
05
1&
#1850
1!
1:
1#
15
0&
1'
#1855
0!
0:
0#
05
1&
#1860
15
0&
0'
1(
#1865
05
1&
#1870
1!
1:
1#
15
0&
1'
#1875
0!
0:
0#
05
1&
#1880
15
0&
0'
0(
1)
#1885
05
1&
#1890
1!
1:
1#
15
0&
1'
#1895
0!
0:
0#
05
1&
#1900
15
0%
0&
0'
1(
#1905
05
1&
#1910
1!
1:
1#
15
0&
1'
#1915
0!
0:
0#
05
1&
#1920
15
1%
0&
0'
0(
0)
0*
0+
0,
1-
#1925
05
1&
#1930
1!
1:
1#
15
0&
1'
#1935
0!
0:
0#
05
1&
#1940
15
0&
0'
1(
#1945
05
1&
#1950
1!
1:
1#
15
0&
1'
#1955
0!
0:
0#
05
1&
#1960
15
0&
0'
0(
1)
#1965
05
1&
#1970
1!
1:
1#
15
0&
1'
#1975
0!
0:
0#
05
1&
#1980
15
0%
0&
0'
1(
#1985
05
1&
#1990
1!
1:
1#
15
0&
1'
#1995
0!
0:
0#
05
1&
#2000
1"
1<
15
1%
07
0&
0'
0(
0)
1*
#2005
05
1&
#2010
1?
1=
1!
1:
1#
15
0&
1'
#2015
0!
0?
0=
0:
0#
05
1&
#2020
15
0&
0'
1(
#2025
05
1&
#2030
1?
1=
1!
1:
1#
15
0&
1'
#2035
0!
0?
0=
0:
0#
05
1&
#2040
15
0&
0'
0(
1)
#2045
05
1&
#2050
1?
1=
1!
1:
1#
15
0&
1'
#2055
0!
0?
0=
0:
0#
05
1&
#2060
15
0%
0&
0'
1(
#2065
05
1&
#2070
1?
1=
1!
1:
1#
15
0&
1'
#2075
0!
0?
0=
0:
0#
05
1&
#2080
15
1%
0&
0'
0(
0)
0*
1+
#2085
05
1&
#2090
1?
1=
1!
1:
1#
15
0&
1'
#2095
0!
0?
0=
0:
0#
05
1&
#2100
15
0&
0'
1(
#2105
05
1&
#2110
1?
1=
1!
1:
1#
15
0&
1'
#2115
0!
0?
0=
0:
0#
05
1&
#2120
15
0&
0'
0(
1)
#2125
05
1&
#2130
1?
1=
1!
1:
1#
15
0&
1'
#2135
0!
0?
0=
0:
0#
05
1&
#2140
15
0%
0&
0'
1(
#2145
05
1&
#2150
1?
1=
1!
1:
1#
15
0&
1'
#2155
0!
0?
0=
0:
0#
05
1&
#2160
0"
0<
15
1%
17
0&
0'
0(
0)
1*
#2165
05
1&
#2170
1!
1:
1#
15
0&
1'
#2175
0!
0:
0#
05
1&
#2180
15
0&
0'
1(
#2185
05
1&
#2190
1!
1:
1#
15
0&
1'
#2195
0!
0:
0#
05
1&
#2200
15
0&
0'
0(
1)
#2205
05
1&
#2210
1!
1:
1#
15
0&
1'
#2215
0!
0:
0#
05
1&
#2220
15
0%
0&
0'
1(
#2225
05
1&
#2230
1!
1:
1#
15
0&
1'
#2235
0!
0:
0#
05
1&
#2240
15
1%
1$
0&
0'
0(
0)
0*
0+
1,
#2245
05
1&
#2250
1!
1:
1#
15
0&
1'
#2255
0!
0:
0#
05
1&
#2260
15
0&
0'
1(
#2265
05
1&
#2270
1!
1:
1#
15
0&
1'
#2275
0!
0:
0#
05
1&
#2280
15
0&
0'
0(
1)
#2285
05
1&
#2290
1!
1:
1#
15
0&
1'
#2295
0!
0:
0#
05
1&
#2300
15
0%
0&
0'
1(
#2305
05
1&
#2310
1!
1:
1#
15
0&
1'
#2315
0!
0:
0#
05
1&
#2320
1"
1<
15
1%
07
0&
0'
0(
0)
1*
#2325
05
1&
#2330
1?
1=
1!
1:
1#
15
0&
1'
#2335
0!
0?
0=
0:
0#
05
1&
#2340
15
0&
0'
1(
#2345
05
1&
#2350
1?
1=
1!
1:
1#
15
0&
1'
#2355
0!
0?
0=
0:
0#
05
1&
#2360
15
0&
0'
0(
1)
#2365
05
1&
#2370
1?
1=
1!
1:
1#
15
0&
1'
#2375
0!
0?
0=
0:
0#
05
1&
#2380
15
0%
0&
0'
1(
#2385
05
1&
#2390
1?
1=
1!
1:
1#
15
0&
1'
#2395
0!
0?
0=
0:
0#
05
1&
#2400
15
1%
0&
0'
0(
0)
0*
1+
#2405
05
1&
#2410
1?
1=
1!
1:
1#
15
0&
1'
#2415
0!
0?
0=
0:
0#
05
1&
#2420
15
0&
0'
1(
#2425
05
1&
#2430
1?
1=
1!
1:
1#
15
0&
1'
#2435
0!
0?
0=
0:
0#
05
1&
#2440
15
0&
0'
0(
1)
#2445
05
1&
#2450
1?
1=
1!
1:
1#
15
0&
1'
#2455
0!
0?
0=
0:
0#
05
1&
#2460
15
0%
0&
0'
1(
#2465
05
1&
#2470
1?
1=
1!
1:
1#
15
0&
1'
#2475
0!
0?
0=
0:
0#
05
1&
#2480
0"
0<
15
1%
17
0&
0'
0(
0)
1*
#2485
05
1&
#2490
1!
1:
1#
15
0&
1'
#2495
0!
0:
0#
05
1&
#2500
15
0&
0'
1(
#2505
05
1&
#2510
1!
1:
1#
15
0&
1'
#2515
0!
0:
0#
05
1&
#2520
15
0&
0'
0(
1)
#2525
05
1&
#2530
1!
1:
1#
15
0&
1'
#2535
0!
0:
0#
05
1&
#2540
15
0%
0&
0'
1(
#2545
05
1&
#2550
1!
1:
1#
15
0&
1'
#2555
0!
0:
0#
05
1&
#2560
15
1%
0$
0&
0'
0(
0)
0*
0+
0,
0-
0.
#2565
05
1&
