Verilog Codes and Testbenches/andCircuit.v
module andCircuit(a,b,c,d,e,f,g,h,i,in1,in2,in3,in4,t,n,r,k,m);

    input a,b,c,d,e,f,g,h,i,in1,in2,in3,in4;
    output t,k,m,n,r;

    wire j,k1,l,m1,n1,o,p,q,r1,s;

    not(j,a);
    nand(k,c,d);
    and(k1,k,in3);
    xnor(l,e,f);
    xor(m,g,h,i);
    and(m1,m,in4);
    and(n,j,b);
    and(n1,n,in1);
    or(o,b,m1);
    nand(p,l,m1);
    and(q,n1,o,p);
    and(r,k1,o,p);
    and(r1,r,in2);
    xor(s,q,r1);
    or(t,n1,s,r1);

endmodule

andCircuitTest.v
`timescale 1ps/1ps
module test();

    reg a,b,c,d,e,f,g,h,i,in1,in2,in3,in4;
    wire t,n,k,r,m;

    andCircuit uut(.a(a),.b(b),.c(c),.d(d),.e(e),.f(f),.g(g),.h(h),.i(i),.in1(in1),.in2(in2),.in3(in3),.in4(in4),.t(t),.n(n),.r(r),.k(k),.m(m));

    initial begin
		$dumpfile("andCircuit.vcd");
     	$dumpvars(0,test);

		// Initialize Inputs
		a = 1'b0;
		b = 1'b0;
        c = 1'b0;
        d = 1'b0;
        e = 1'b0;
        f = 1'b0;
        g = 1'b0;
        h = 1'b0;
        i = 1'b0;

        //Change these for control pin inputs
        in1 = 1'b1;
        in2 = 1'b1;
        in3 = 1'b1;
        in4 = 1'b1;

		#2565 $finish;//global reset
	end

    //Generating all possible 64 combinations
	always #5 a=~a;
	always #10 b=~b;
    always #20 c=~c;
    always #40 d=~d;
    always #80 e=~e;
    always #160 f=~f;
    always #320 g=~g;
    always #640 h=~h;
    always #1280 i=~i;

    //printing values for each new test vector
	always #5
    $display("t=%b n=%b r=%b k=%b m=%b",t,n,r,k,m);

endmodule

Executables/andCircuit.vcd
$date
	Wed Oct 27 01:53:05 2021
$end
$version
	Icarus Verilog
$end
$timescale
	1ps
$end
$scope module test $end
$var wire 1 ! t $end
$var wire 1 " r $end
$var wire 1 # n $end
$var wire 1 $ m $end
$var wire 1 % k $end
$var reg 1 & a $end
$var reg 1 ' b $end
$var reg 1 ( c $end
$var reg 1 ) d $end
$var reg 1 * e $end
$var reg 1 + f $end
$var reg 1 , g $end
$var reg 1 - h $end
$var reg 1 . i $end
$var reg 1 / in1 $end
$var reg 1 0 in2 $end
$var reg 1 1 in3 $end
$var reg 1 2 in4 $end
$scope module uut $end
$var wire 1 & a $end
$var wire 1 ' b $end
$var wire 1 ( c $end
$var wire 1 ) d $end
$var wire 1 * e $end
$var wire 1 + f $end
$var wire 1 , g $end
$var wire 1 - h $end
$var wire 1 . i $end
$var wire 1 / in1 $end
$var wire 1 0 in2 $end
$var wire 1 1 in3 $end
$var wire 1 2 in4 $end
$var wire 1 3 j $end
$var wire 1 % k $end
$var wire 1 4 k1 $end
$var wire 1 5 l $end
$var wire 1 $ m $end
$var wire 1 6 m1 $end
$var wire 1 # n $end
$var wire 1 7 n1 $end
$var wire 1 8 o $end
$var wire 1 9 p $end
$var wire 1 : q $end
$var wire 1 " r $end
$var wire 1 ; r1 $end
$var wire 1 < s $end
$var wire 1 ! t $end
$upscope $end
$upscope $end
$enddefinitions $end
#0
$dumpvars
0<
0;
0:
19
08
07
06
15
14
13
12
11
10
1/
0.
0-
0,
0+
0*
0)
0(
0'
0&
1%
0$
0#
0"
0!
$end
#5
03
1&
#10
1:
0<
1!
17
1;
1#
1"
13
18
0&
1'
#15
1<
0:
07
0#
03
1&
#20
0!
0<
0;
0"
13
08
0&
0'
1(
#25
03
1&
#30
1:
0<
1!
17
1;
1#
1"
13
18
0&
1'
#35
1<
0:
07
0#
03
1&
#40
0!
0<
0;
0"
13
08
0&
0'
0(
1)
#45
03
1&
#50
1:
0<
1!
17
1;
1#
1"
13
18
0&
1'
#55
1<
0:
07
0#
03
1&
#60
0!
0<
0;
0"
04
13
08
0%
0&
0'
1(
#65
03
1&
#70
1<
1:
1!
17
1#
13
18
0&
1'
#75
0!
0<
0:
07
0#
03
1&
#80
14
13
08
1%
05
0&
0'
0(
0)
1*
#85
03
1&
#90
1:
0<
1!
17
1;
1#
1"
13
18
0&
1'
#95
1<
0:
07
0#
03
1&
#100
0!
0<
0;
0"
13
08
0&
0'
1(
#105
03
1&
#110
1:
0<
1!
17
1;
1#
1"
13
18
0&
1'
#115
1<
0:
07
0#
03
1&
#120
0!
0<
0;
0"
13
08
0&
0'
0(
1)
#125
03
1&
#130
1:
0<
1!
17
1;
1#
1"
13
18
0&
1'
#135
1<
0:
07
0#
03
1&
#140
0!
0<
0;
0"
04
13
08
0%
0&
0'
1(
#145
03
1&
#150
1<
1:
1!
17
1#
13
18
0&
1'
#155
0!
0<
0:
07
0#
03
1&
#160
14
13
08
1%
0&
0'
0(
0)
0*
1+
#165
03
1&
#170
1:
0<
1!
17
1;
1#
1"
13
18
0&
1'
#175
1<
0:
07
0#
03
1&
#180
0!
0<
0;
0"
13
08
0&
0'
1(
#185
03
1&
#190
1:
0<
1!
17
1;
1#
1"
13
18
0&
1'
#195
1<
0:
07
0#
03
1&
#200
0!
0<
0;
0"
13
08
0&
0'
0(
1)
#205
03
1&
#210
1:
0<
1!
17
1;
1#
1"
13
18
0&
1'
#215
1<
0:
07
0#
03
1&
#220
0!
0<
0;
0"
04
13
08
0%
0&
0'
1(
#225
03
1&
#230
1<
1:
1!
17
1#
13
18
0&
1'
#235
0!
0<
0:
07
0#
03
1&
#240
14
13
08
1%
15
0&
0'
0(
0)
1*
#245
03
1&
#250
1:
0<
1!
17
1;
1#
1"
13
18
0&
1'
#255
1<
0:
07
0#
03
1&
#260
0!
0<
0;
0"
13
08
0&
0'
1(
#265
03
1&
#270
1:
0<
1!
17
1;
1#
1"
13
18
0&
1'
#275
1<
0:
07
0#
03
1&
#280
0!
0<
0;
0"
13
08
0&
0'
0(
1)
#285
03
1&
#290
1:
0<
1!
17
1;
1#
1"
13
18
0&
1'
#295
1<
0:
07
0#
03
1&
#300
0!
0<
0;
0"
04
13
08
0%
0&
0'
1(
#305
03
1&
#310
1<
1:
1!
17
1#
13
18
0&
1'
#315
0!
0<
0:
07
0#
03
1&
#320
09
14
16
13
18
1%
1$
0&
0'
0(
0)
0*
0+
1,
#325
03
1&
#330
1!
17
1#
13
0&
1'
#335
0!
07
0#
03
1&
#340
13
0&
0'
1(
#345
03
1&
#350
1!
17
1#
13
0&
1'
#355
0!
07
0#
03
1&
#360
13
0&
0'
0(
1)
#365
03
1&
#370
1!
17
1#
13
0&
1'
#375
0!
07
0#
03
1&
#380
04
13
0%
0&
0'
1(
#385
03
1&
#390
1!
17
1#
13
0&
1'
#395
0!
07
0#
03
1&
#400
1<
1!
1;
1"
14
19
13
1%
05
0&
0'
0(
0)
1*
#405
03
1&
#410
0<
1:
17
1#
13
0&
1'
#415
1<
0:
07
0#
03
1&
#420
13
0&
0'
1(
#425
03
1&
#430
0<
1:
17
1#
13
0&
1'
#435
1<
0:
07
0#
03
1&
#440
13
0&
0'
0(
1)
#445
03
1&
#450
0<
1:
17
1#
13
0&
1'
#455
1<
0:
07
0#
03
1&
#460
0!
0<
0;
0"
04
13
0%
0&
0'
1(
#465
03
1&
#470
1<
1:
1!
17
1#
13
0&
1'
#475
0!
0<
0:
07
0#
03
1&
#480
1<
1!
1;
1"
14
13
1%
0&
0'
0(
0)
0*
1+
#485
03
1&
#490
0<
1:
17
1#
13
0&
1'
#495
1<
0:
07
0#
03
1&
#500
13
0&
0'
1(
#505
03
1&
#510
0<
1:
17
1#
13
0&
1'
#515
1<
0:
07
0#
03
1&
#520
13
0&
0'
0(
1)
#525
03
1&
#530
0<
1:
17
1#
13
0&
1'
#535
1<
0:
07
0#
03
1&
#540
0!
0<
0;
0"
04
13
0%
0&
0'
1(
#545
03
1&
#550
1<
1:
1!
17
1#
13
0&
1'
#555
0!
0<
0:
07
0#
03
1&
#560
14
09
13
1%
15
0&
0'
0(
0)
1*
#565
03
1&
#570
1!
17
1#
13
0&
1'
#575
0!
07
0#
03
1&
#580
13
0&
0'
1(
#585
03
1&
#590
1!
17
1#
13
0&
1'
#595
0!
07
0#
03
1&
#600
13
0&
0'
0(
1)
#605
03
1&
#610
1!
17
1#
13
0&
1'
#615
0!
07
0#
03
1&
#620
04
13
0%
0&
0'
1(
#625
03
1&
#630
1!
17
1#
13
0&
1'
#635
0!
07
0#
03
1&
#640
14
13
1%
0&
0'
0(
0)
0*
0+
0,
1-
#645
03
1&
#650
1!
17
1#
13
0&
1'
#655
0!
07
0#
03
1&
#660
13
0&
0'
1(
#665
03
1&
#670
1!
17
1#
13
0&
1'
#675
0!
07
0#
03
1&
#680
13
0&
0'
0(
1)
#685
03
1&
#690
1!
17
1#
13
0&
1'
#695
0!
07
0#
03
1&
#700
04
13
0%
0&
0'
1(
#705
03
1&
#710
1!
17
1#
13
0&
1'
#715
0!
07
0#
03
1&
#720
1<
1!
1;
1"
14
19
13
1%
05
0&
0'
0(
0)
1*
#725
03
1&
#730
0<
1:
17
1#
13
0&
1'
#735
1<
0:
07
0#
03
1&
#740
13
0&
0'
1(
#745
03
1&
#750
0<
1:
17
1#
13
0&
1'
#755
1<
0:
07
0#
03
1&
#760
13
0&
0'
0(
1)
#765
03
1&
#770
0<
1:
17
1#
13
0&
1'
#775
1<
0:
07
0#
03
1&
#780
0!
0<
0;
0"
04
13
0%
0&
0'
1(
#785
03
1&
#790
1<
1:
1!
17
1#
13
0&
1'
#795
0!
0<
0:
07
0#
03
1&
#800
1<
1!
1;
1"
14
13
1%
0&
0'
0(
0)
0*
1+
#805
03
1&
#810
0<
1:
17
1#
13
0&
1'
#815
1<
0:
07
0#
03
1&
#820
13
0&
0'
1(
#825
03
1&
#830
0<
1:
17
1#
13
0&
1'
#835
1<
0:
07
0#
03
1&
#840
13
0&
0'
0(
1)
#845
03
1&
#850
0<
1:
17
1#
13
0&
1'
#855
1<
0:
07
0#
03
1&
#860
0!
0<
0;
0"
04
13
0%
0&
0'
1(
#865
03
1&
#870
1<
1:
1!
17
1#
13
0&
1'
#875
0!
0<
0:
07
0#
03
1&
#880
14
09
13
1%
15
0&
0'
0(
0)
1*
#885
03
1&
#890
1!
17
1#
13
0&
1'
#895
0!
07
0#
03
1&
#900
13
0&
0'
1(
#905
03
1&
#910
1!
17
1#
13
0&
1'
#915
0!
07
0#
03
1&
#920
13
0&
0'
0(
1)
#925
03
1&
#930
1!
17
1#
13
0&
1'
#935
0!
07
0#
03
1&
#940
04
13
0%
0&
0'
1(
#945
03
1&
#950
1!
17
1#
13
0&
1'
#955
0!
07
0#
03
1&
#960
08
19
14
06
13
1%
0$
0&
0'
0(
0)
0*
0+
1,
#965
03
1&
#970
1:
0<
1!
17
1;
1#
1"
13
18
0&
1'
#975
1<
0:
07
0#
03
1&
#980
0!
0<
0;
0"
13
08
0&
0'
1(
#985
03
1&
#990
1:
0<
1!
17
1;
1#
1"
13
18
0&
1'
#995
1<
0:
07
0#
03
1&
#1000
0!
0<
0;
0"
13
08
0&
0'
0(
1)
#1005
03
1&
#1010
1:
0<
1!
17
1;
1#
1"
13
18
0&
1'
#1015
1<
0:
07
0#
03
1&
#1020
0!
0<
0;
0"
04
13
08
0%
0&
0'
1(
#1025
03
1&
#1030
1<
1:
1!
17
1#
13
18
0&
1'
#1035
0!
0<
0:
07
0#
03
1&
#1040
14
13
08
1%
05
0&
0'
0(
0)
1*
#1045
03
1&
#1050
1:
0<
1!
17
1;
1#
1"
13
18
0&
1'
#1055
1<
0:
07
0#
03
1&
#1060
0!
0<
0;
0"
13
08
0&
0'
1(
#1065
03
1&
#1070
1:
0<
1!
17
1;
1#
1"
13
18
0&
1'
#1075
1<
0:
07
0#
03
1&
#1080
0!
0<
0;
0"
13
08
0&
0'
0(
1)
#1085
03
1&
#1090
1:
0<
1!
17
1;
1#
1"
13
18
0&
1'
#1095
1<
0:
07
0#
03
1&
#1100
0!
0<
0;
0"
04
13
08
0%
0&
0'
1(
#1105
03
1&
#1110
1<
1:
1!
17
1#
13
18
0&
1'
#1115
0!
0<
0:
07
0#
03
1&
#1120
14
13
08
1%
0&
0'
0(
0)
0*
1+
#1125
03
1&
#1130
1:
0<
1!
17
1;
1#
1"
13
18
0&
1'
#1135
1<
0:
07
0#
03
1&
#1140
0!
0<
0;
0"
13
08
0&
0'
1(
#1145
03
1&
#1150
1:
0<
1!
17
1;
1#
1"
13
18
0&
1'
#1155
1<
0:
07
0#
03
1&
#1160
0!
0<
0;
0"
13
08
0&
0'
0(
1)
#1165
03
1&
#1170
1:
0<
1!
17
1;
1#
1"
13
18
0&
1'
#1175
1<
0:
07
0#
03
1&
#1180
0!
0<
0;
0"
04
13
08
0%
0&
0'
1(
#1185
03
1&
#1190
1<
1:
1!
17
1#
13
18
0&
1'
#1195
0!
0<
0:
07
0#
03
1&
#1200
14
13
08
1%
15
0&
0'
0(
0)
1*
#1205
03
1&
#1210
1:
0<
1!
17
1;
1#
1"
13
18
0&
1'
#1215
1<
0:
07
0#
03
1&
#1220
0!
0<
0;
0"
13
08
0&
0'
1(
#1225
03
1&
#1230
1:
0<
1!
17
1;
1#
1"
13
18
0&
1'
#1235
1<
0:
07
0#
03
1&
#1240
0!
0<
0;
0"
13
08
0&
0'
0(
1)
#1245
03
1&
#1250
1:
0<
1!
17
1;
1#
1"
13
18
0&
1'
#1255
1<
0:
07
0#
03
1&
#1260
0!
0<
0;
0"
04
13
08
0%
0&
0'
1(
#1265
03
1&
#1270
1<
1:
1!
17
1#
13
18
0&
1'
#1275
0!
0<
0:
07
0#
03
1&
#1280
09
14
16
13
18
1%
1$
0&
0'
0(
0)
0*
0+
0,
0-
1.
#1285
03
1&
#1290
1!
17
1#
13
0&
1'
#1295
0!
07
0#
03
1&
#1300
13
0&
0'
1(
#1305
03
1&
#1310
1!
17
1#
13
0&
1'
#1315
0!
07
0#
03
1&
#1320
13
0&
0'
0(
1)
#1325
03
1&
#1330
1!
17
1#
13
0&
1'
#1335
0!
07
0#
03
1&
#1340
04
13
0%
0&
0'
1(
#1345
03
1&
#1350
1!
17
1#
13
0&
1'
#1355
0!
07
0#
03
1&
#1360
1<
1!
1;
1"
14
19
13
1%
05
0&
0'
0(
0)
1*
#1365
03
1&
#1370
0<
1:
17
1#
13
0&
1'
#1375
1<
0:
07
0#
03
1&
#1380
13
0&
0'
1(
#1385
03
1&
#1390
0<
1:
17
1#
13
0&
1'
#1395
1<
0:
07
0#
03
1&
#1400
13
0&
0'
0(
1)
#1405
03
1&
#1410
0<
1:
17
1#
13
0&
1'
#1415
1<
0:
07
0#
03
1&
#1420
0!
0<
0;
0"
04
13
0%
0&
0'
1(
#1425
03
1&
#1430
1<
1:
1!
17
1#
13
0&
1'
#1435
0!
0<
0:
07
0#
03
1&
#1440
1<
1!
1;
1"
14
13
1%
0&
0'
0(
0)
0*
1+
#1445
03
1&
#1450
0<
1:
17
1#
13
0&
1'
#1455
1<
0:
07
0#
03
1&
#1460
13
0&
0'
1(
#1465
03
1&
#1470
0<
1:
17
1#
13
0&
1'
#1475
1<
0:
07
0#
03
1&
#1480
13
0&
0'
0(
1)
#1485
03
1&
#1490
0<
1:
17
1#
13
0&
1'
#1495
1<
0:
07
0#
03
1&
#1500
0!
0<
0;
0"
04
13
0%
0&
0'
1(
#1505
03
1&
#1510
1<
1:
1!
17
1#
13
0&
1'
#1515
0!
0<
0:
07
0#
03
1&
#1520
14
09
13
1%
15
0&
0'
0(
0)
1*
#1525
03
1&
#1530
1!
17
1#
13
0&
1'
#1535
0!
07
0#
03
1&
#1540
13
0&
0'
1(
#1545
03
1&
#1550
1!
17
1#
13
0&
1'
#1555
0!
07
0#
03
1&
#1560
13
0&
0'
0(
1)
#1565
03
1&
#1570
1!
17
1#
13
0&
1'
#1575
0!
07
0#
03
1&
#1580
04
13
0%
0&
0'
1(
#1585
03
1&
#1590
1!
17
1#
13
0&
1'
#1595
0!
07
0#
03
1&
#1600
08
19
14
06
13
1%
0$
0&
0'
0(
0)
0*
0+
1,
#1605
03
1&
#1610
1:
0<
1!
17
1;
1#
1"
13
18
0&
1'
#1615
1<
0:
07
0#
03
1&
#1620
0!
0<
0;
0"
13
08
0&
0'
1(
#1625
03
1&
#1630
1:
0<
1!
17
1;
1#
1"
13
18
0&
1'
#1635
1<
0:
07
0#
03
1&
#1640
0!
0<
0;
0"
13
08
0&
0'
0(
1)
#1645
03
1&
#1650
1:
0<
1!
17
1;
1#
1"
13
18
0&
1'
#1655
1<
0:
07
0#
03
1&
#1660
0!
0<
0;
0"
04
13
08
0%
0&
0'
1(
#1665
03
1&
#1670
1<
1:
1!
17
1#
13
18
0&
1'
#1675
0!
0<
0:
07
0#
03
1&
#1680
14
13
08
1%
05
0&
0'
0(
0)
1*
#1685
03
1&
#1690
1:
0<
1!
17
1;
1#
1"
13
18
0&
1'
#1695
1<
0:
07
0#
03
1&
#1700
0!
0<
0;
0"
13
08
0&
0'
1(
#1705
03
1&
#1710
1:
0<
1!
17
1;
1#
1"
13
18
0&
1'
#1715
1<
0:
07
0#
03
1&
#1720
0!
0<
0;
0"
13
08
0&
0'
0(
1)
#1725
03
1&
#1730
1:
0<
1!
17
1;
1#
1"
13
18
0&
1'
#1735
1<
0:
07
0#
03
1&
#1740
0!
0<
0;
0"
04
13
08
0%
0&
0'
1(
#1745
03
1&
#1750
1<
1:
1!
17
1#
13
18
0&
1'
#1755
0!
0<
0:
07
0#
03
1&
#1760
14
13
08
1%
0&
0'
0(
0)
0*
1+
#1765
03
1&
#1770
1:
0<
1!
17
1;
1#
1"
13
18
0&
1'
#1775
1<
0:
07
0#
03
1&
#1780
0!
0<
0;
0"
13
08
0&
0'
1(
#1785
03
1&
#1790
1:
0<
1!
17
1;
1#
1"
13
18
0&
1'
#1795
1<
0:
07
0#
03
1&
#1800
0!
0<
0;
0"
13
08
0&
0'
0(
1)
#1805
03
1&
#1810
1:
0<
1!
17
1;
1#
1"
13
18
0&
1'
#1815
1<
0:
07
0#
03
1&
#1820
0!
0<
0;
0"
04
13
08
0%
0&
0'
1(
#1825
03
1&
#1830
1<
1:
1!
17
1#
13
18
0&
1'
#1835
0!
0<
0:
07
0#
03
1&
#1840
14
13
08
1%
15
0&
0'
0(
0)
1*
#1845
03
1&
#1850
1:
0<
1!
17
1;
1#
1"
13
18
0&
1'
#1855
1<
0:
07
0#
03
1&
#1860
0!
0<
0;
0"
13
08
0&
0'
1(
#1865
03
1&
#1870
1:
0<
1!
17
1;
1#
1"
13
18
0&
1'
#1875
1<
0:
07
0#
03
1&
#1880
0!
0<
0;
0"
13
08
0&
0'
0(
1)
#1885
03
1&
#1890
1:
0<
1!
17
1;
1#
1"
13
18
0&
1'
#1895
1<
0:
07
0#
03
1&
#1900
0!
0<
0;
0"
04
13
08
0%
0&
0'
1(
#1905
03
1&
#1910
1<
1:
1!
17
1#
13
18
0&
1'
#1915
0!
0<
0:
07
0#
03
1&
#1920
14
13
08
1%
0&
0'
0(
0)
0*
0+
0,
1-
#1925
03
1&
#1930
1:
0<
1!
17
1;
1#
1"
13
18
0&
1'
#1935
1<
0:
07
0#
03
1&
#1940
0!
0<
0;
0"
13
08
0&
0'
1(
#1945
03
1&
#1950
1:
0<
1!
17
1;
1#
1"
13
18
0&
1'
#1955
1<
0:
07
0#
03
1&
#1960
0!
0<
0;
0"
13
08
0&
0'
0(
1)
#1965
03
1&
#1970
1:
0<
1!
17
1;
1#
1"
13
18
0&
1'
#1975
1<
0:
07
0#
03
1&
#1980
0!
0<
0;
0"
04
13
08
0%
0&
0'
1(
#1985
03
1&
#1990
1<
1:
1!
17
1#
13
18
0&
1'
#1995
0!
0<
0:
07
0#
03
1&
#2000
14
13
08
1%
05
0&
0'
0(
0)
1*
#2005
03
1&
#2010
1:
0<
1!
17
1;
1#
1"
13
18
0&
1'
#2015
1<
0:
07
0#
03
1&
#2020
0!
0<
0;
0"
13
08
0&
0'
1(
#2025
03
1&
#2030
1:
0<
1!
17
1;
1#
1"
13
18
0&
1'
#2035
1<
0:
07
0#
03
1&
#2040
0!
0<
0;
0"
13
08
0&
0'
0(
1)
#2045
03
1&
#2050
1:
0<
1!
17
1;
1#
1"
13
18
0&
1'
#2055
1<
0:
07
0#
03
1&
#2060
0!
0<
0;
0"
04
13
08
0%
0&
0'
1(
#2065
03
1&
#2070
1<
1:
1!
17
1#
13
18
0&
1'
#2075
0!
0<
0:
07
0#
03
1&
#2080
14
13
08
1%
0&
0'
0(
0)
0*
1+
#2085
03
1&
#2090
1:
0<
1!
17
1;
1#
1"
13
18
0&
1'
#2095
1<
0:
07
0#
03
1&
#2100
0!
0<
0;
0"
13
08
0&
0'
1(
#2105
03
1&
#2110
1:
0<
1!
17
1;
1#
1"
13
18
0&
1'
#2115
1<
0:
07
0#
03
1&
#2120
0!
0<
0;
0"
13
08
0&
0'
0(
1)
#2125
03
1&
#2130
1:
0<
1!
17
1;
1#
1"
13
18
0&
1'
#2135
1<
0:
07
0#
03
1&
#2140
0!
0<
0;
0"
04
13
08
0%
0&
0'
1(
#2145
03
1&
#2150
1<
1:
1!
17
1#
13
18
0&
1'
#2155
0!
0<
0:
07
0#
03
1&
#2160
14
13
08
1%
15
0&
0'
0(
0)
1*
#2165
03
1&
#2170
1:
0<
1!
17
1;
1#
1"
13
18
0&
1'
#2175
1<
0:
07
0#
03
1&
#2180
0!
0<
0;
0"
13
08
0&
0'
1(
#2185
03
1&
#2190
1:
0<
1!
17
1;
1#
1"
13
18
0&
1'
#2195
1<
0:
07
0#
03
1&
#2200
0!
0<
0;
0"
13
08
0&
0'
0(
1)
#2205
03
1&
#2210
1:
0<
1!
17
1;
1#
1"
13
18
0&
1'
#2215
1<
0:
07
0#
03
1&
#2220
0!
0<
0;
0"
04
13
08
0%
0&
0'
1(
#2225
03
1&
#2230
1<
1:
1!
17
1#
13
18
0&
1'
#2235
0!
0<
0:
07
0#
03
1&
#2240
09
14
16
13
18
1%
1$
0&
0'
0(
0)
0*
0+
1,
#2245
03
1&
#2250
1!
17
1#
13
0&
1'
#2255
0!
07
0#
03
1&
#2260
13
0&
0'
1(
#2265
03
1&
#2270
1!
17
1#
13
0&
1'
#2275
0!
07
0#
03
1&
#2280
13
0&
0'
0(
1)
#2285
03
1&
#2290
1!
17
1#
13
0&
1'
#2295
0!
07
0#
03
1&
#2300
04
13
0%
0&
0'
1(
#2305
03
1&
#2310
1!
17
1#
13
0&
1'
#2315
0!
07
0#
03
1&
#2320
1<
1!
1;
1"
14
19
13
1%
05
0&
0'
0(
0)
1*
#2325
03
1&
#2330
0<
1:
17
1#
13
0&
1'
#2335
1<
0:
07
0#
03
1&
#2340
13
0&
0'
1(
#2345
03
1&
#2350
0<
1:
17
1#
13
0&
1'
#2355
1<
0:
07
0#
03
1&
#2360
13
0&
0'
0(
1)
#2365
03
1&
#2370
0<
1:
17
1#
13
0&
1'
#2375
1<
0:
07
0#
03
1&
#2380
0!
0<
0;
0"
04
13
0%
0&
0'
1(
#2385
03
1&
#2390
1<
1:
1!
17
1#
13
0&
1'
#2395
0!
0<
0:
07
0#
03
1&
#2400
1<
1!
1;
1"
14
13
1%
0&
0'
0(
0)
0*
1+
#2405
03
1&
#2410
0<
1:
17
1#
13
0&
1'
#2415
1<
0:
07
0#
03
1&
#2420
13
0&
0'
1(
#2425
03
1&
#2430
0<
1:
17
1#
13
0&
1'
#2435
1<
0:
07
0#
03
1&
#2440
13
0&
0'
0(
1)
#2445
03
1&
#2450
0<
1:
17
1#
13
0&
1'
#2455
1<
0:
07
0#
03
1&
#2460
0!
0<
0;
0"
04
13
0%
0&
0'
1(
#2465
03
1&
#2470
1<
1:
1!
17
1#
13
0&
1'
#2475
0!
0<
0:
07
0#
03
1&
#2480
14
09
13
1%
15
0&
0'
0(
0)
1*
#2485
03
1&
#2490
1!
17
1#
13
0&
1'
#2495
0!
07
0#
03
1&
#2500
13
0&
0'
1(
#2505
03
1&
#2510
1!
17
1#
13
0&
1'
#2515
0!
07
0#
03
1&
#2520
13
0&
0'
0(
1)
#2525
03
1&
#2530
1!
17
1#
13
0&
1'
#2535
0!
07
0#
03
1&
#2540
04
13
0%
0&
0'
1(
#2545
03
1&
#2550
1!
17
1#
13
0&
1'
#2555
0!
07
0#
03
1&
#2560
08
19
14
06
13
1%
0$
0&
0'
0(
0)
0*
0+
0,
0-
0.
#2565
03
1&
