Verilog Codes and Testbenches/combinational.v
module basicCircuit(a,b,c,d,e,f,g,h,i,t);

    input a,b,c,d,e,f,g,h,i;
    output t;

    wire j,k,l,m,n,o,p,q,r,s;

    not(j,a);
    nand(k,c,d);
    xnor(l,e,f);
    xor(m,g,h,i);
    and(n,j,b);
    or(o,b,m);
    nand(p,l,m);
    and(q,n,o,p);
    and(r,k,o,p);
    xor(s,q,r);
    or(t,n,s,r);

endmodule

combinationalTest.v
`timescale 1ps/1ps
module test();

    reg a,b,c,d,e,f,g,h,i;
    wire t;

    basicCircuit uut(.a(a),.b(b),.c(c),.d(d),.e(e),.f(f),.g(g),.h(h),.i(i),.t(t));

    initial begin
		$dumpfile("basicCircuit.vcd");
     	$dumpvars(0,test);
		// Initialize Inputs
		a = 1'b0;
		b = 1'b0;
        c = 1'b0;
        d = 1'b0;
        e = 1'b0;
        f = 1'b0;
        g = 1'b0;
        h = 1'b0;
        i = 1'b0;

		#2565 $finish;//global reset
	end

    //Generating all possible 64 combinations
	always #5 a=~a;
	always #10 b=~b;
    always #20 c=~c;
    always #40 d=~d;
    always #80 e=~e;
    always #160 f=~f;
    always #320 g=~g;
    always #640 h=~h;
    always #1280 i=~i;

    //printing values for each new test vector
	always #5
    $display("%b",t);

endmodule

Executables/basicCircuit.vcd
$date
	Wed Oct 27 01:52:56 2021
$end
$version
	Icarus Verilog
$end
$timescale
	1ps
$end
$scope module test $end
$var wire 1 ! t $end
$var reg 1 " a $end
$var reg 1 # b $end
$var reg 1 $ c $end
$var reg 1 % d $end
$var reg 1 & e $end
$var reg 1 ' f $end
$var reg 1 ( g $end
$var reg 1 ) h $end
$var reg 1 * i $end
$scope module uut $end
$var wire 1 " a $end
$var wire 1 # b $end
$var wire 1 $ c $end
$var wire 1 % d $end
$var wire 1 & e $end
$var wire 1 ' f $end
$var wire 1 ( g $end
$var wire 1 ) h $end
$var wire 1 * i $end
$var wire 1 + j $end
$var wire 1 , k $end
$var wire 1 - l $end
$var wire 1 . m $end
$var wire 1 / n $end
$var wire 1 0 o $end
$var wire 1 1 p $end
$var wire 1 2 q $end
$var wire 1 3 r $end
$var wire 1 4 s $end
$var wire 1 ! t $end
$upscope $end
$upscope $end
$enddefinitions $end
#0
$dumpvars
04
03
02
11
00
0/
0.
1-
1,
1+
0*
0)
0(
0'
0&
0%
0$
0#
0"
0!
$end
#5
0+
1"
#10
12
04
1!
1/
13
1+
10
0"
1#
#15
14
02
0/
0+
1"
#20
0!
04
03
1+
00
0"
0#
1$
#25
0+
1"
#30
12
04
1!
1/
13
1+
10
0"
1#
#35
14
02
0/
0+
1"
#40
0!
04
03
1+
00
0"
0#
0$
1%
#45
0+
1"
#50
12
04
1!
1/
13
1+
10
0"
1#
#55
14
02
0/
0+
1"
#60
0!
04
03
1+
00
0,
0"
0#
1$
#65
0+
1"
#70
14
12
1!
1/
1+
10
0"
1#
#75
0!
04
02
0/
0+
1"
#80
1+
00
1,
0-
0"
0#
0$
0%
1&
#85
0+
1"
#90
12
04
1!
1/
13
1+
10
0"
1#
#95
14
02
0/
0+
1"
#100
0!
04
03
1+
00
0"
0#
1$
#105
0+
1"
#110
12
04
1!
1/
13
1+
10
0"
1#
#115
14
02
0/
0+
1"
#120
0!
04
03
1+
00
0"
0#
0$
1%
#125
0+
1"
#130
12
04
1!
1/
13
1+
10
0"
1#
#135
14
02
0/
0+
1"
#140
0!
04
03
1+
00
0,
0"
0#
1$
#145
0+
1"
#150
14
12
1!
1/
1+
10
0"
1#
#155
0!
04
02
0/
0+
1"
#160
1+
00
1,
0"
0#
0$
0%
0&
1'
#165
0+
1"
#170
12
04
1!
1/
13
1+
10
0"
1#
#175
14
02
0/
0+
1"
#180
0!
04
03
1+
00
0"
0#
1$
#185
0+
1"
#190
12
04
1!
1/
13
1+
10
0"
1#
#195
14
02
0/
0+
1"
#200
0!
04
03
1+
00
0"
0#
0$
1%
#205
0+
1"
#210
12
04
1!
1/
13
1+
10
0"
1#
#215
14
02
0/
0+
1"
#220
0!
04
03
1+
00
0,
0"
0#
1$
#225
0+
1"
#230
14
12
1!
1/
1+
10
0"
1#
#235
0!
04
02
0/
0+
1"
#240
1+
00
1,
1-
0"
0#
0$
0%
1&
#245
0+
1"
#250
12
04
1!
1/
13
1+
10
0"
1#
#255
14
02
0/
0+
1"
#260
0!
04
03
1+
00
0"
0#
1$
#265
0+
1"
#270
12
04
1!
1/
13
1+
10
0"
1#
#275
14
02
0/
0+
1"
#280
0!
04
03
1+
00
0"
0#
0$
1%
#285
0+
1"
#290
12
04
1!
1/
13
1+
10
0"
1#
#295
14
02
0/
0+
1"
#300
0!
04
03
1+
00
0,
0"
0#
1$
#305
0+
1"
#310
14
12
1!
1/
1+
10
0"
1#
#315
0!
04
02
0/
0+
1"
#320
01
1+
1,
1.
0"
0#
0$
0%
0&
0'
1(
#325
0+
1"
#330
1!
1/
1+
0"
1#
#335
0!
0/
0+
1"
#340
1+
0"
0#
1$
#345
0+
1"
#350
1!
1/
1+
0"
1#
#355
0!
0/
0+
1"
#360
1+
0"
0#
0$
1%
#365
0+
1"
#370
1!
1/
1+
0"
1#
#375
0!
0/
0+
1"
#380
1+
0,
0"
0#
1$
#385
0+
1"
#390
1!
1/
1+
0"
1#
#395
0!
0/
0+
1"
#400
14
1!
13
11
1+
1,
0-
0"
0#
0$
0%
1&
#405
0+
1"
#410
04
12
1/
1+
0"
1#
#415
14
02
0/
0+
1"
#420
1+
0"
0#
1$
#425
0+
1"
#430
04
12
1/
1+
0"
1#
#435
14
02
0/
0+
1"
#440
1+
0"
0#
0$
1%
#445
0+
1"
#450
04
12
1/
1+
0"
1#
#455
14
02
0/
0+
1"
#460
0!
04
03
1+
0,
0"
0#
1$
#465
0+
1"
#470
14
12
1!
1/
1+
0"
1#
#475
0!
04
02
0/
0+
1"
#480
14
1!
13
1+
1,
0"
0#
0$
0%
0&
1'
#485
0+
1"
#490
04
12
1/
1+
0"
1#
#495
14
02
0/
0+
1"
#500
1+
0"
0#
1$
#505
0+
1"
#510
04
12
1/
1+
0"
1#
#515
14
02
0/
0+
1"
#520
1+
0"
0#
0$
1%
#525
0+
1"
#530
04
12
1/
1+
0"
1#
#535
14
02
0/
0+
1"
#540
0!
04
03
1+
0,
0"
0#
1$
#545
0+
1"
#550
14
12
1!
1/
1+
0"
1#
#555
0!
04
02
0/
0+
1"
#560
01
1+
1,
1-
0"
0#
0$
0%
1&
#565
0+
1"
#570
1!
1/
1+
0"
1#
#575
0!
0/
0+
1"
#580
1+
0"
0#
1$
#585
0+
1"
#590
1!
1/
1+
0"
1#
#595
0!
0/
0+
1"
#600
1+
0"
0#
0$
1%
#605
0+
1"
#610
1!
1/
1+
0"
1#
#615
0!
0/
0+
1"
#620
1+
0,
0"
0#
1$
#625
0+
1"
#630
1!
1/
1+
0"
1#
#635
0!
0/
0+
1"
#640
1+
1,
0"
0#
0$
0%
0&
0'
0(
1)
#645
0+
1"
#650
1!
1/
1+
0"
1#
#655
0!
0/
0+
1"
#660
1+
0"
0#
1$
#665
0+
1"
#670
1!
1/
1+
0"
1#
#675
0!
0/
0+
1"
#680
1+
0"
0#
0$
1%
#685
0+
1"
#690
1!
1/
1+
0"
1#
#695
0!
0/
0+
1"
#700
1+
0,
0"
0#
1$
#705
0+
1"
#710
1!
1/
1+
0"
1#
#715
0!
0/
0+
1"
#720
14
1!
13
11
1+
1,
0-
0"
0#
0$
0%
1&
#725
0+
1"
#730
04
12
1/
1+
0"
1#
#735
14
02
0/
0+
1"
#740
1+
0"
0#
1$
#745
0+
1"
#750
04
12
1/
1+
0"
1#
#755
14
02
0/
0+
1"
#760
1+
0"
0#
0$
1%
#765
0+
1"
#770
04
12
1/
1+
0"
1#
#775
14
02
0/
0+
1"
#780
0!
04
03
1+
0,
0"
0#
1$
#785
0+
1"
#790
14
12
1!
1/
1+
0"
1#
#795
0!
04
02
0/
0+
1"
#800
14
1!
13
1+
1,
0"
0#
0$
0%
0&
1'
#805
0+
1"
#810
04
12
1/
1+
0"
1#
#815
14
02
0/
0+
1"
#820
1+
0"
0#
1$
#825
0+
1"
#830
04
12
1/
1+
0"
1#
#835
14
02
0/
0+
1"
#840
1+
0"
0#
0$
1%
#845
0+
1"
#850
04
12
1/
1+
0"
1#
#855
14
02
0/
0+
1"
#860
0!
04
03
1+
0,
0"
0#
1$
#865
0+
1"
#870
14
12
1!
1/
1+
0"
1#
#875
0!
04
02
0/
0+
1"
#880
01
1+
1,
1-
0"
0#
0$
0%
1&
#885
0+
1"
#890
1!
1/
1+
0"
1#
#895
0!
0/
0+
1"
#900
1+
0"
0#
1$
#905
0+
1"
#910
1!
1/
1+
0"
1#
#915
0!
0/
0+
1"
#920
1+
0"
0#
0$
1%
#925
0+
1"
#930
1!
1/
1+
0"
1#
#935
0!
0/
0+
1"
#940
1+
0,
0"
0#
1$
#945
0+
1"
#950
1!
1/
1+
0"
1#
#955
0!
0/
0+
1"
#960
11
1+
00
1,
0.
0"
0#
0$
0%
0&
0'
1(
#965
0+
1"
#970
12
04
1!
1/
13
1+
10
0"
1#
#975
14
02
0/
0+
1"
#980
0!
04
03
1+
00
0"
0#
1$
#985
0+
1"
#990
12
04
1!
1/
13
1+
10
0"
1#
#995
14
02
0/
0+
1"
#1000
0!
04
03
1+
00
0"
0#
0$
1%
#1005
0+
1"
#1010
12
04
1!
1/
13
1+
10
0"
1#
#1015
14
02
0/
0+
1"
#1020
0!
04
03
1+
00
0,
0"
0#
1$
#1025
0+
1"
#1030
14
12
1!
1/
1+
10
0"
1#
#1035
0!
04
02
0/
0+
1"
#1040
1+
00
1,
0-
0"
0#
0$
0%
1&
#1045
0+
1"
#1050
12
04
1!
1/
13
1+
10
0"
1#
#1055
14
02
0/
0+
1"
#1060
0!
04
03
1+
00
0"
0#
1$
#1065
0+
1"
#1070
12
04
1!
1/
13
1+
10
0"
1#
#1075
14
02
0/
0+
1"
#1080
0!
04
03
1+
00
0"
0#
0$
1%
#1085
0+
1"
#1090
12
04
1!
1/
13
1+
10
0"
1#
#1095
14
02
0/
0+
1"
#1100
0!
04
03
1+
00
0,
0"
0#
1$
#1105
0+
1"
#1110
14
12
1!
1/
1+
10
0"
1#
#1115
0!
04
02
0/
0+
1"
#1120
1+
00
1,
0"
0#
0$
0%
0&
1'
#1125
0+
1"
#1130
12
04
1!
1/
13
1+
10
0"
1#
#1135
14
02
0/
0+
1"
#1140
0!
04
03
1+
00
0"
0#
1$
#1145
0+
1"
#1150
12
04
1!
1/
13
1+
10
0"
1#
#1155
14
02
0/
0+
1"
#1160
0!
04
03
1+
00
0"
0#
0$
1%
#1165
0+
1"
#1170
12
04
1!
1/
13
1+
10
0"
1#
#1175
14
02
0/
0+
1"
#1180
0!
04
03
1+
00
0,
0"
0#
1$
#1185
0+
1"
#1190
14
12
1!
1/
1+
10
0"
1#
#1195
0!
04
02
0/
0+
1"
#1200
1+
00
1,
1-
0"
0#
0$
0%
1&
#1205
0+
1"
#1210
12
04
1!
1/
13
1+
10
0"
1#
#1215
14
02
0/
0+
1"
#1220
0!
04
03
1+
00
0"
0#
1$
#1225
0+
1"
#1230
12
04
1!
1/
13
1+
10
0"
1#
#1235
14
02
0/
0+
1"
#1240
0!
04
03
1+
00
0"
0#
0$
1%
#1245
0+
1"
#1250
12
04
1!
1/
13
1+
10
0"
1#
#1255
14
02
0/
0+
1"
#1260
0!
04
03
1+
00
0,
0"
0#
1$
#1265
0+
1"
#1270
14
12
1!
1/
1+
10
0"
1#
#1275
0!
04
02
0/
0+
1"
#1280
01
1+
1,
1.
0"
0#
0$
0%
0&
0'
0(
0)
1*
#1285
0+
1"
#1290
1!
1/
1+
0"
1#
#1295
0!
0/
0+
1"
#1300
1+
0"
0#
1$
#1305
0+
1"
#1310
1!
1/
1+
0"
1#
#1315
0!
0/
0+
1"
#1320
1+
0"
0#
0$
1%
#1325
0+
1"
#1330
1!
1/
1+
0"
1#
#1335
0!
0/
0+
1"
#1340
1+
0,
0"
0#
1$
#1345
0+
1"
#1350
1!
1/
1+
0"
1#
#1355
0!
0/
0+
1"
#1360
14
1!
13
11
1+
1,
0-
0"
0#
0$
0%
1&
#1365
0+
1"
#1370
04
12
1/
1+
0"
1#
#1375
14
02
0/
0+
1"
#1380
1+
0"
0#
1$
#1385
0+
1"
#1390
04
12
1/
1+
0"
1#
#1395
14
02
0/
0+
1"
#1400
1+
0"
0#
0$
1%
#1405
0+
1"
#1410
04
12
1/
1+
0"
1#
#1415
14
02
0/
0+
1"
#1420
0!
04
03
1+
0,
0"
0#
1$
#1425
0+
1"
#1430
14
12
1!
1/
1+
0"
1#
#1435
0!
04
02
0/
0+
1"
#1440
14
1!
13
1+
1,
0"
0#
0$
0%
0&
1'
#1445
0+
1"
#1450
04
12
1/
1+
0"
1#
#1455
14
02
0/
0+
1"
#1460
1+
0"
0#
1$
#1465
0+
1"
#1470
04
12
1/
1+
0"
1#
#1475
14
02
0/
0+
1"
#1480
1+
0"
0#
0$
1%
#1485
0+
1"
#1490
04
12
1/
1+
0"
1#
#1495
14
02
0/
0+
1"
#1500
0!
04
03
1+
0,
0"
0#
1$
#1505
0+
1"
#1510
14
12
1!
1/
1+
0"
1#
#1515
0!
04
02
0/
0+
1"
#1520
01
1+
1,
1-
0"
0#
0$
0%
1&
#1525
0+
1"
#1530
1!
1/
1+
0"
1#
#1535
0!
0/
0+
1"
#1540
1+
0"
0#
1$
#1545
0+
1"
#1550
1!
1/
1+
0"
1#
#1555
0!
0/
0+
1"
#1560
1+
0"
0#
0$
1%
#1565
0+
1"
#1570
1!
1/
1+
0"
1#
#1575
0!
0/
0+
1"
#1580
1+
0,
0"
0#
1$
#1585
0+
1"
#1590
1!
1/
1+
0"
1#
#1595
0!
0/
0+
1"
#1600
11
1+
00
1,
0.
0"
0#
0$
0%
0&
0'
1(
#1605
0+
1"
#1610
12
04
1!
1/
13
1+
10
0"
1#
#1615
14
02
0/
0+
1"
#1620
0!
04
03
1+
00
0"
0#
1$
#1625
0+
1"
#1630
12
04
1!
1/
13
1+
10
0"
1#
#1635
14
02
0/
0+
1"
#1640
0!
04
03
1+
00
0"
0#
0$
1%
#1645
0+
1"
#1650
12
04
1!
1/
13
1+
10
0"
1#
#1655
14
02
0/
0+
1"
#1660
0!
04
03
1+
00
0,
0"
0#
1$
#1665
0+
1"
#1670
14
12
1!
1/
1+
10
0"
1#
#1675
0!
04
02
0/
0+
1"
#1680
1+
00
1,
0-
0"
0#
0$
0%
1&
#1685
0+
1"
#1690
12
04
1!
1/
13
1+
10
0"
1#
#1695
14
02
0/
0+
1"
#1700
0!
04
03
1+
00
0"
0#
1$
#1705
0+
1"
#1710
12
04
1!
1/
13
1+
10
0"
1#
#1715
14
02
0/
0+
1"
#1720
0!
04
03
1+
00
0"
0#
0$
1%
#1725
0+
1"
#1730
12
04
1!
1/
13
1+
10
0"
1#
#1735
14
02
0/
0+
1"
#1740
0!
04
03
1+
00
0,
0"
0#
1$
#1745
0+
1"
#1750
14
12
1!
1/
1+
10
0"
1#
#1755
0!
04
02
0/
0+
1"
#1760
1+
00
1,
0"
0#
0$
0%
0&
1'
#1765
0+
1"
#1770
12
04
1!
1/
13
1+
10
0"
1#
#1775
14
02
0/
0+
1"
#1780
0!
04
03
1+
00
0"
0#
1$
#1785
0+
1"
#1790
12
04
1!
1/
13
1+
10
0"
1#
#1795
14
02
0/
0+
1"
#1800
0!
04
03
1+
00
0"
0#
0$
1%
#1805
0+
1"
#1810
12
04
1!
1/
13
1+
10
0"
1#
#1815
14
02
0/
0+
1"
#1820
0!
04
03
1+
00
0,
0"
0#
1$
#1825
0+
1"
#1830
14
12
1!
1/
1+
10
0"
1#
#1835
0!
04
02
0/
0+
1"
#1840
1+
00
1,
1-
0"
0#
0$
0%
1&
#1845
0+
1"
#1850
12
04
1!
1/
13
1+
10
0"
1#
#1855
14
02
0/
0+
1"
#1860
0!
04
03
1+
00
0"
0#
1$
#1865
0+
1"
#1870
12
04
1!
1/
13
1+
10
0"
1#
#1875
14
02
0/
0+
1"
#1880
0!
04
03
1+
00
0"
0#
0$
1%
#1885
0+
1"
#1890
12
04
1!
1/
13
1+
10
0"
1#
#1895
14
02
0/
0+
1"
#1900
0!
04
03
1+
00
0,
0"
0#
1$
#1905
0+
1"
#1910
14
12
1!
1/
1+
10
0"
1#
#1915
0!
04
02
0/
0+
1"
#1920
1+
00
1,
0"
0#
0$
0%
0&
0'
0(
1)
#1925
0+
1"
#1930
12
04
1!
1/
13
1+
10
0"
1#
#1935
14
02
0/
0+
1"
#1940
0!
04
03
1+
00
0"
0#
1$
#1945
0+
1"
#1950
12
04
1!
1/
13
1+
10
0"
1#
#1955
14
02
0/
0+
1"
#1960
0!
04
03
1+
00
0"
0#
0$
1%
#1965
0+
1"
#1970
12
04
1!
1/
13
1+
10
0"
1#
#1975
14
02
0/
0+
1"
#1980
0!
04
03
1+
00
0,
0"
0#
1$
#1985
0+
1"
#1990
14
12
1!
1/
1+
10
0"
1#
#1995
0!
04
02
0/
0+
1"
#2000
1+
00
1,
0-
0"
0#
0$
0%
1&
#2005
0+
1"
#2010
12
04
1!
1/
13
1+
10
0"
1#
#2015
14
02
0/
0+
1"
#2020
0!
04
03
1+
00
0"
0#
1$
#2025
0+
1"
#2030
12
04
1!
1/
13
1+
10
0"
1#
#2035
14
02
0/
0+
1"
#2040
0!
04
03
1+
00
0"
0#
0$
1%
#2045
0+
1"
#2050
12
04
1!
1/
13
1+
10
0"
1#
#2055
14
02
0/
0+
1"
#2060
0!
04
03
1+
00
0,
0"
0#
1$
#2065
0+
1"
#2070
14
12
1!
1/
1+
10
0"
1#
#2075
0!
04
02
0/
0+
1"
#2080
1+
00
1,
0"
0#
0$
0%
0&
1'
#2085
0+
1"
#2090
12
04
1!
1/
13
1+
10
0"
1#
#2095
14
02
0/
0+
1"
#2100
0!
04
03
1+
00
0"
0#
1$
#2105
0+
1"
#2110
12
04
1!
1/
13
1+
10
0"
1#
#2115
14
02
0/
0+
1"
#2120
0!
04
03
1+
00
0"
0#
0$
1%
#2125
0+
1"
#2130
12
04
1!
1/
13
1+
10
0"
1#
#2135
14
02
0/
0+
1"
#2140
0!
04
03
1+
00
0,
0"
0#
1$
#2145
0+
1"
#2150
14
12
1!
1/
1+
10
0"
1#
#2155
0!
04
02
0/
0+
1"
#2160
1+
00
1,
1-
0"
0#
0$
0%
1&
#2165
0+
1"
#2170
12
04
1!
1/
13
1+
10
0"
1#
#2175
14
02
0/
0+
1"
#2180
0!
04
03
1+
00
0"
0#
1$
#2185
0+
1"
#2190
12
04
1!
1/
13
1+
10
0"
1#
#2195
14
02
0/
0+
1"
#2200
0!
04
03
1+
00
0"
0#
0$
1%
#2205
0+
1"
#2210
12
04
1!
1/
13
1+
10
0"
1#
#2215
14
02
0/
0+
1"
#2220
0!
04
03
1+
00
0,
0"
0#
1$
#2225
0+
1"
#2230
14
12
1!
1/
1+
10
0"
1#
#2235
0!
04
02
0/
0+
1"
#2240
01
1+
1,
1.
0"
0#
0$
0%
0&
0'
1(
#2245
0+
1"
#2250
1!
1/
1+
0"
1#
#2255
0!
0/
0+
1"
#2260
1+
0"
0#
1$
#2265
0+
1"
#2270
1!
1/
1+
0"
1#
#2275
0!
0/
0+
1"
#2280
1+
0"
0#
0$
1%
#2285
0+
1"
#2290
1!
1/
1+
0"
1#
#2295
0!
0/
0+
1"
#2300
1+
0,
0"
0#
1$
#2305
0+
1"
#2310
1!
1/
1+
0"
1#
#2315
0!
0/
0+
1"
#2320
14
1!
13
11
1+
1,
0-
0"
0#
0$
0%
1&
#2325
0+
1"
#2330
04
12
1/
1+
0"
1#
#2335
14
02
0/
0+
1"
#2340
1+
0"
0#
1$
#2345
0+
1"
#2350
04
12
1/
1+
0"
1#
#2355
14
02
0/
0+
1"
#2360
1+
0"
0#
0$
1%
#2365
0+
1"
#2370
04
12
1/
1+
0"
1#
#2375
14
02
0/
0+
1"
#2380
0!
04
03
1+
0,
0"
0#
1$
#2385
0+
1"
#2390
14
12
1!
1/
1+
0"
1#
#2395
0!
04
02
0/
0+
1"
#2400
14
1!
13
1+
1,
0"
0#
0$
0%
0&
1'
#2405
0+
1"
#2410
04
12
1/
1+
0"
1#
#2415
14
02
0/
0+
1"
#2420
1+
0"
0#
1$
#2425
0+
1"
#2430
04
12
1/
1+
0"
1#
#2435
14
02
0/
0+
1"
#2440
1+
0"
0#
0$
1%
#2445
0+
1"
#2450
04
12
1/
1+
0"
1#
#2455
14
02
0/
0+
1"
#2460
0!
04
03
1+
0,
0"
0#
1$
#2465
0+
1"
#2470
14
12
1!
1/
1+
0"
1#
#2475
0!
04
02
0/
0+
1"
#2480
01
1+
1,
1-
0"
0#
0$
0%
1&
#2485
0+
1"
#2490
1!
1/
1+
0"
1#
#2495
0!
0/
0+
1"
#2500
1+
0"
0#
1$
#2505
0+
1"
#2510
1!
1/
1+
0"
1#
#2515
0!
0/
0+
1"
#2520
1+
0"
0#
0$
1%
#2525
0+
1"
#2530
1!
1/
1+
0"
1#
#2535
0!
0/
0+
1"
#2540
1+
0,
0"
0#
1$
#2545
0+
1"
#2550
1!
1/
1+
0"
1#
#2555
0!
0/
0+
1"
#2560
11
1+
00
1,
0.
0"
0#
0$
0%
0&
0'
0(
0)
0*
#2565
0+
1"
