muxCircuit.v
primitive mux (y, a, b, sel);
  output y;
  input a, b, sel;
  table
    // a  b  sel  :  y
       0  ?   0   :  0;
       1  ?   0   :  1;
       ?  0   1   :  0;
       ?  1   1   :  1;
  endtable
endprimitive

module muxCircuit(a,b,c,d,e,f,g,h,i,in1,in2,in3,in4,in5,in6,in7,in8,t,n,r,k,m);

    input a,b,c,d,e,f,g,h,i,in1,in2,in3,in4,in5,in6,in7,in8;
    output t,k,m,n,r;

    wire j,k2,l,m2,n2,o,p,q,r2,s;

    not(j,a);
    nand(k,c,d);
    mux(k2,k,in3,in7);
    xnor(l,e,f);
    xor(m,g,h,i);
    mux(m2,m,in4,in8);
    and(n,j,b);
    mux(n2,n,in1,in5);
    or(o,b,m2);
    nand(p,l,m2);
    and(q,n2,o,p);
    and(r,k2,o,p);
    mux(r2,r,in2,in6);
    xor(s,q,r2);
    or(t,n2,s,r2);

endmodule

muxCircuitTest.v
`timescale 1ps/1ps
module test();

    reg a,b,c,d,e,f,g,h,i,in1,in2,in3,in4,in5,in6,in7,in8;
    wire t,n,k,r,m;

    muxCircuit uut(.a(a),.b(b),.c(c),.d(d),.e(e),.f(f),.g(g),.h(h),.i(i),.in1(in1),.in2(in2),.in3(in3),.in4(in4),.in5(in5),.in6(in6),.in7(in7),.in8(in8),.t(t),.n(n),.r(r),.k(k),.m(m));

    initial begin
		$dumpfile("muxCircuit.vcd");
     	$dumpvars(0,test);

		// Initialize Inputs
		a = 1'b0;
		b = 1'b0;
        c = 1'b0;
        d = 1'b0;
        e = 1'b0;
        f = 1'b0;
        g = 1'b0;
        h = 1'b0;
        i = 1'b0;

        //Change these for control pin inputs
        in1 = 1'b0;
        in2 = 1'b0;
        in3 = 1'b0;
        in4 = 1'b0;
        in5 = 1'b0;
        in6 = 1'b0;
        in7 = 1'b0;
        in8 = 1'b0;

		#2565 $finish;//global reset
	end

    //Generating all possible 64 combinations
	always #5 a=~a;
	always #10 b=~b;
    always #20 c=~c;
    always #40 d=~d;
    always #80 e=~e;
    always #160 f=~f;
    always #320 g=~g;
    always #640 h=~h;
    always #1280 i=~i;

    //printing values for each new test vector
	always #5
    $display("t=%b n=%b r=%b k=%b m=%b",t,n,r,k,m);

endmodule

Executables/muxCircuit.vcd
$date
	Wed Oct 27 01:53:46 2021
$end
$version
	Icarus Verilog
$end
$timescale
	1ps
$end
$scope module test $end
$var wire 1 ! t $end
$var wire 1 " r $end
$var wire 1 # n $end
$var wire 1 $ m $end
$var wire 1 % k $end
$var reg 1 & a $end
$var reg 1 ' b $end
$var reg 1 ( c $end
$var reg 1 ) d $end
$var reg 1 * e $end
$var reg 1 + f $end
$var reg 1 , g $end
$var reg 1 - h $end
$var reg 1 . i $end
$var reg 1 / in1 $end
$var reg 1 0 in2 $end
$var reg 1 1 in3 $end
$var reg 1 2 in4 $end
$var reg 1 3 in5 $end
$var reg 1 4 in6 $end
$var reg 1 5 in7 $end
$var reg 1 6 in8 $end
$scope module uut $end
$var wire 1 & a $end
$var wire 1 ' b $end
$var wire 1 ( c $end
$var wire 1 ) d $end
$var wire 1 * e $end
$var wire 1 + f $end
$var wire 1 , g $end
$var wire 1 - h $end
$var wire 1 . i $end
$var wire 1 / in1 $end
$var wire 1 0 in2 $end
$var wire 1 1 in3 $end
$var wire 1 2 in4 $end
$var wire 1 3 in5 $end
$var wire 1 4 in6 $end
$var wire 1 5 in7 $end
$var wire 1 6 in8 $end
$var wire 1 7 j $end
$var wire 1 % k $end
$var wire 1 8 k2 $end
$var wire 1 9 l $end
$var wire 1 $ m $end
$var wire 1 : m2 $end
$var wire 1 # n $end
$var wire 1 ; n2 $end
$var wire 1 < o $end
$var wire 1 = p $end
$var wire 1 > q $end
$var wire 1 " r $end
$var wire 1 ? r2 $end
$var wire 1 @ s $end
$var wire 1 ! t $end
$upscope $end
$upscope $end
$enddefinitions $end
#0
$dumpvars
0@
0?
0>
1=
0<
0;
0:
19
18
17
06
05
04
03
02
01
00
0/
0.
0-
0,
0+
0*
0)
0(
0'
0&
1%
0$
0#
0"
0!
$end
#5
07
1&
#10
1>
0@
1!
1;
1?
1#
1"
17
1<
0&
1'
#15
1@
0>
0;
0#
07
1&
#20
0!
0@
0?
0"
17
0<
0&
0'
1(
#25
07
1&
#30
1>
0@
1!
1;
1?
1#
1"
17
1<
0&
1'
#35
1@
0>
0;
0#
07
1&
#40
0!
0@
0?
0"
17
0<
0&
0'
0(
1)
#45
07
1&
#50
1>
0@
1!
1;
1?
1#
1"
17
1<
0&
1'
#55
1@
0>
0;
0#
07
1&
#60
0!
0@
0?
0"
08
17
0<
0%
0&
0'
1(
#65
07
1&
#70
1@
1>
1!
1;
1#
17
1<
0&
1'
#75
0!
0@
0>
0;
0#
07
1&
#80
18
17
0<
1%
09
0&
0'
0(
0)
1*
#85
07
1&
#90
1>
0@
1!
1;
1?
1#
1"
17
1<
0&
1'
#95
1@
0>
0;
0#
07
1&
#100
0!
0@
0?
0"
17
0<
0&
0'
1(
#105
07
1&
#110
1>
0@
1!
1;
1?
1#
1"
17
1<
0&
1'
#115
1@
0>
0;
0#
07
1&
#120
0!
0@
0?
0"
17
0<
0&
0'
0(
1)
#125
07
1&
#130
1>
0@
1!
1;
1?
1#
1"
17
1<
0&
1'
#135
1@
0>
0;
0#
07
1&
#140
0!
0@
0?
0"
08
17
0<
0%
0&
0'
1(
#145
07
1&
#150
1@
1>
1!
1;
1#
17
1<
0&
1'
#155
0!
0@
0>
0;
0#
07
1&
#160
18
17
0<
1%
0&
0'
0(
0)
0*
1+
#165
07
1&
#170
1>
0@
1!
1;
1?
1#
1"
17
1<
0&
1'
#175
1@
0>
0;
0#
07
1&
#180
0!
0@
0?
0"
17
0<
0&
0'
1(
#185
07
1&
#190
1>
0@
1!
1;
1?
1#
1"
17
1<
0&
1'
#195
1@
0>
0;
0#
07
1&
#200
0!
0@
0?
0"
17
0<
0&
0'
0(
1)
#205
07
1&
#210
1>
0@
1!
1;
1?
1#
1"
17
1<
0&
1'
#215
1@
0>
0;
0#
07
1&
#220
0!
0@
0?
0"
08
17
0<
0%
0&
0'
1(
#225
07
1&
#230
1@
1>
1!
1;
1#
17
1<
0&
1'
#235
0!
0@
0>
0;
0#
07
1&
#240
18
17
0<
1%
19
0&
0'
0(
0)
1*
#245
07
1&
#250
1>
0@
1!
1;
1?
1#
1"
17
1<
0&
1'
#255
1@
0>
0;
0#
07
1&
#260
0!
0@
0?
0"
17
0<
0&
0'
1(
#265
07
1&
#270
1>
0@
1!
1;
1?
1#
1"
17
1<
0&
1'
#275
1@
0>
0;
0#
07
1&
#280
0!
0@
0?
0"
17
0<
0&
0'
0(
1)
#285
07
1&
#290
1>
0@
1!
1;
1?
1#
1"
17
1<
0&
1'
#295
1@
0>
0;
0#
07
1&
#300
0!
0@
0?
0"
08
17
0<
0%
0&
0'
1(
#305
07
1&
#310
1@
1>
1!
1;
1#
17
1<
0&
1'
#315
0!
0@
0>
0;
0#
07
1&
#320
0=
18
1:
17
1<
1%
1$
0&
0'
0(
0)
0*
0+
1,
#325
07
1&
#330
1!
1;
1#
17
0&
1'
#335
0!
0;
0#
07
1&
#340
17
0&
0'
1(
#345
07
1&
#350
1!
1;
1#
17
0&
1'
#355
0!
0;
0#
07
1&
#360
17
0&
0'
0(
1)
#365
07
1&
#370
1!
1;
1#
17
0&
1'
#375
0!
0;
0#
07
1&
#380
08
17
0%
0&
0'
1(
#385
07
1&
#390
1!
1;
1#
17
0&
1'
#395
0!
0;
0#
07
1&
#400
1@
1!
1?
1"
18
1=
17
1%
09
0&
0'
0(
0)
1*
#405
07
1&
#410
0@
1>
1;
1#
17
0&
1'
#415
1@
0>
0;
0#
07
1&
#420
17
0&
0'
1(
#425
07
1&
#430
0@
1>
1;
1#
17
0&
1'
#435
1@
0>
0;
0#
07
1&
#440
17
0&
0'
0(
1)
#445
07
1&
#450
0@
1>
1;
1#
17
0&
1'
#455
1@
0>
0;
0#
07
1&
#460
0!
0@
0?
0"
08
17
0%
0&
0'
1(
#465
07
1&
#470
1@
1>
1!
1;
1#
17
0&
1'
#475
0!
0@
0>
0;
0#
07
1&
#480
1@
1!
1?
1"
18
17
1%
0&
0'
0(
0)
0*
1+
#485
07
1&
#490
0@
1>
1;
1#
17
0&
1'
#495
1@
0>
0;
0#
07
1&
#500
17
0&
0'
1(
#505
07
1&
#510
0@
1>
1;
1#
17
0&
1'
#515
1@
0>
0;
0#
07
1&
#520
17
0&
0'
0(
1)
#525
07
1&
#530
0@
1>
1;
1#
17
0&
1'
#535
1@
0>
0;
0#
07
1&
#540
0!
0@
0?
0"
08
17
0%
0&
0'
1(
#545
07
1&
#550
1@
1>
1!
1;
1#
17
0&
1'
#555
0!
0@
0>
0;
0#
07
1&
#560
18
0=
17
1%
19
0&
0'
0(
0)
1*
#565
07
1&
#570
1!
1;
1#
17
0&
1'
#575
0!
0;
0#
07
1&
#580
17
0&
0'
1(
#585
07
1&
#590
1!
1;
1#
17
0&
1'
#595
0!
0;
0#
07
1&
#600
17
0&
0'
0(
1)
#605
07
1&
#610
1!
1;
1#
17
0&
1'
#615
0!
0;
0#
07
1&
#620
08
17
0%
0&
0'
1(
#625
07
1&
#630
1!
1;
1#
17
0&
1'
#635
0!
0;
0#
07
1&
#640
18
17
1%
0&
0'
0(
0)
0*
0+
0,
1-
#645
07
1&
#650
1!
1;
1#
17
0&
1'
#655
0!
0;
0#
07
1&
#660
17
0&
0'
1(
#665
07
1&
#670
1!
1;
1#
17
0&
1'
#675
0!
0;
0#
07
1&
#680
17
0&
0'
0(
1)
#685
07
1&
#690
1!
1;
1#
17
0&
1'
#695
0!
0;
0#
07
1&
#700
08
17
0%
0&
0'
1(
#705
07
1&
#710
1!
1;
1#
17
0&
1'
#715
0!
0;
0#
07
1&
#720
1@
1!
1?
1"
18
1=
17
1%
09
0&
0'
0(
0)
1*
#725
07
1&
#730
0@
1>
1;
1#
17
0&
1'
#735
1@
0>
0;
0#
07
1&
#740
17
0&
0'
1(
#745
07
1&
#750
0@
1>
1;
1#
17
0&
1'
#755
1@
0>
0;
0#
07
1&
#760
17
0&
0'
0(
1)
#765
07
1&
#770
0@
1>
1;
1#
17
0&
1'
#775
1@
0>
0;
0#
07
1&
#780
0!
0@
0?
0"
08
17
0%
0&
0'
1(
#785
07
1&
#790
1@
1>
1!
1;
1#
17
0&
1'
#795
0!
0@
0>
0;
0#
07
1&
#800
1@
1!
1?
1"
18
17
1%
0&
0'
0(
0)
0*
1+
#805
07
1&
#810
0@
1>
1;
1#
17
0&
1'
#815
1@
0>
0;
0#
07
1&
#820
17
0&
0'
1(
#825
07
1&
#830
0@
1>
1;
1#
17
0&
1'
#835
1@
0>
0;
0#
07
1&
#840
17
0&
0'
0(
1)
#845
07
1&
#850
0@
1>
1;
1#
17
0&
1'
#855
1@
0>
0;
0#
07
1&
#860
0!
0@
0?
0"
08
17
0%
0&
0'
1(
#865
07
1&
#870
1@
1>
1!
1;
1#
17
0&
1'
#875
0!
0@
0>
0;
0#
07
1&
#880
18
0=
17
1%
19
0&
0'
0(
0)
1*
#885
07
1&
#890
1!
1;
1#
17
0&
1'
#895
0!
0;
0#
07
1&
#900
17
0&
0'
1(
#905
07
1&
#910
1!
1;
1#
17
0&
1'
#915
0!
0;
0#
07
1&
#920
17
0&
0'
0(
1)
#925
07
1&
#930
1!
1;
1#
17
0&
1'
#935
0!
0;
0#
07
1&
#940
08
17
0%
0&
0'
1(
#945
07
1&
#950
1!
1;
1#
17
0&
1'
#955
0!
0;
0#
07
1&
#960
0<
1=
18
0:
17
1%
0$
0&
0'
0(
0)
0*
0+
1,
#965
07
1&
#970
1>
0@
1!
1;
1?
1#
1"
17
1<
0&
1'
#975
1@
0>
0;
0#
07
1&
#980
0!
0@
0?
0"
17
0<
0&
0'
1(
#985
07
1&
#990
1>
0@
1!
1;
1?
1#
1"
17
1<
0&
1'
#995
1@
0>
0;
0#
07
1&
#1000
0!
0@
0?
0"
17
0<
0&
0'
0(
1)
#1005
07
1&
#1010
1>
0@
1!
1;
1?
1#
1"
17
1<
0&
1'
#1015
1@
0>
0;
0#
07
1&
#1020
0!
0@
0?
0"
08
17
0<
0%
0&
0'
1(
#1025
07
1&
#1030
1@
1>
1!
1;
1#
17
1<
0&
1'
#1035
0!
0@
0>
0;
0#
07
1&
#1040
18
17
0<
1%
09
0&
0'
0(
0)
1*
#1045
07
1&
#1050
1>
0@
1!
1;
1?
1#
1"
17
1<
0&
1'
#1055
1@
0>
0;
0#
07
1&
#1060
0!
0@
0?
0"
17
0<
0&
0'
1(
#1065
07
1&
#1070
1>
0@
1!
1;
1?
1#
1"
17
1<
0&
1'
#1075
1@
0>
0;
0#
07
1&
#1080
0!
0@
0?
0"
17
0<
0&
0'
0(
1)
#1085
07
1&
#1090
1>
0@
1!
1;
1?
1#
1"
17
1<
0&
1'
#1095
1@
0>
0;
0#
07
1&
#1100
0!
0@
0?
0"
08
17
0<
0%
0&
0'
1(
#1105
07
1&
#1110
1@
1>
1!
1;
1#
17
1<
0&
1'
#1115
0!
0@
0>
0;
0#
07
1&
#1120
18
17
0<
1%
0&
0'
0(
0)
0*
1+
#1125
07
1&
#1130
1>
0@
1!
1;
1?
1#
1"
17
1<
0&
1'
#1135
1@
0>
0;
0#
07
1&
#1140
0!
0@
0?
0"
17
0<
0&
0'
1(
#1145
07
1&
#1150
1>
0@
1!
1;
1?
1#
1"
17
1<
0&
1'
#1155
1@
0>
0;
0#
07
1&
#1160
0!
0@
0?
0"
17
0<
0&
0'
0(
1)
#1165
07
1&
#1170
1>
0@
1!
1;
1?
1#
1"
17
1<
0&
1'
#1175
1@
0>
0;
0#
07
1&
#1180
0!
0@
0?
0"
08
17
0<
0%
0&
0'
1(
#1185
07
1&
#1190
1@
1>
1!
1;
1#
17
1<
0&
1'
#1195
0!
0@
0>
0;
0#
07
1&
#1200
18
17
0<
1%
19
0&
0'
0(
0)
1*
#1205
07
1&
#1210
1>
0@
1!
1;
1?
1#
1"
17
1<
0&
1'
#1215
1@
0>
0;
0#
07
1&
#1220
0!
0@
0?
0"
17
0<
0&
0'
1(
#1225
07
1&
#1230
1>
0@
1!
1;
1?
1#
1"
17
1<
0&
1'
#1235
1@
0>
0;
0#
07
1&
#1240
0!
0@
0?
0"
17
0<
0&
0'
0(
1)
#1245
07
1&
#1250
1>
0@
1!
1;
1?
1#
1"
17
1<
0&
1'
#1255
1@
0>
0;
0#
07
1&
#1260
0!
0@
0?
0"
08
17
0<
0%
0&
0'
1(
#1265
07
1&
#1270
1@
1>
1!
1;
1#
17
1<
0&
1'
#1275
0!
0@
0>
0;
0#
07
1&
#1280
0=
18
1:
17
1<
1%
1$
0&
0'
0(
0)
0*
0+
0,
0-
1.
#1285
07
1&
#1290
1!
1;
1#
17
0&
1'
#1295
0!
0;
0#
07
1&
#1300
17
0&
0'
1(
#1305
07
1&
#1310
1!
1;
1#
17
0&
1'
#1315
0!
0;
0#
07
1&
#1320
17
0&
0'
0(
1)
#1325
07
1&
#1330
1!
1;
1#
17
0&
1'
#1335
0!
0;
0#
07
1&
#1340
08
17
0%
0&
0'
1(
#1345
07
1&
#1350
1!
1;
1#
17
0&
1'
#1355
0!
0;
0#
07
1&
#1360
1@
1!
1?
1"
18
1=
17
1%
09
0&
0'
0(
0)
1*
#1365
07
1&
#1370
0@
1>
1;
1#
17
0&
1'
#1375
1@
0>
0;
0#
07
1&
#1380
17
0&
0'
1(
#1385
07
1&
#1390
0@
1>
1;
1#
17
0&
1'
#1395
1@
0>
0;
0#
07
1&
#1400
17
0&
0'
0(
1)
#1405
07
1&
#1410
0@
1>
1;
1#
17
0&
1'
#1415
1@
0>
0;
0#
07
1&
#1420
0!
0@
0?
0"
08
17
0%
0&
0'
1(
#1425
07
1&
#1430
1@
1>
1!
1;
1#
17
0&
1'
#1435
0!
0@
0>
0;
0#
07
1&
#1440
1@
1!
1?
1"
18
17
1%
0&
0'
0(
0)
0*
1+
#1445
07
1&
#1450
0@
1>
1;
1#
17
0&
1'
#1455
1@
0>
0;
0#
07
1&
#1460
17
0&
0'
1(
#1465
07
1&
#1470
0@
1>
1;
1#
17
0&
1'
#1475
1@
0>
0;
0#
07
1&
#1480
17
0&
0'
0(
1)
#1485
07
1&
#1490
0@
1>
1;
1#
17
0&
1'
#1495
1@
0>
0;
0#
07
1&
#1500
0!
0@
0?
0"
08
17
0%
0&
0'
1(
#1505
07
1&
#1510
1@
1>
1!
1;
1#
17
0&
1'
#1515
0!
0@
0>
0;
0#
07
1&
#1520
18
0=
17
1%
19
0&
0'
0(
0)
1*
#1525
07
1&
#1530
1!
1;
1#
17
0&
1'
#1535
0!
0;
0#
07
1&
#1540
17
0&
0'
1(
#1545
07
1&
#1550
1!
1;
1#
17
0&
1'
#1555
0!
0;
0#
07
1&
#1560
17
0&
0'
0(
1)
#1565
07
1&
#1570
1!
1;
1#
17
0&
1'
#1575
0!
0;
0#
07
1&
#1580
08
17
0%
0&
0'
1(
#1585
07
1&
#1590
1!
1;
1#
17
0&
1'
#1595
0!
0;
0#
07
1&
#1600
0<
1=
18
0:
17
1%
0$
0&
0'
0(
0)
0*
0+
1,
#1605
07
1&
#1610
1>
0@
1!
1;
1?
1#
1"
17
1<
0&
1'
#1615
1@
0>
0;
0#
07
1&
#1620
0!
0@
0?
0"
17
0<
0&
0'
1(
#1625
07
1&
#1630
1>
0@
1!
1;
1?
1#
1"
17
1<
0&
1'
#1635
1@
0>
0;
0#
07
1&
#1640
0!
0@
0?
0"
17
0<
0&
0'
0(
1)
#1645
07
1&
#1650
1>
0@
1!
1;
1?
1#
1"
17
1<
0&
1'
#1655
1@
0>
0;
0#
07
1&
#1660
0!
0@
0?
0"
08
17
0<
0%
0&
0'
1(
#1665
07
1&
#1670
1@
1>
1!
1;
1#
17
1<
0&
1'
#1675
0!
0@
0>
0;
0#
07
1&
#1680
18
17
0<
1%
09
0&
0'
0(
0)
1*
#1685
07
1&
#1690
1>
0@
1!
1;
1?
1#
1"
17
1<
0&
1'
#1695
1@
0>
0;
0#
07
1&
#1700
0!
0@
0?
0"
17
0<
0&
0'
1(
#1705
07
1&
#1710
1>
0@
1!
1;
1?
1#
1"
17
1<
0&
1'
#1715
1@
0>
0;
0#
07
1&
#1720
0!
0@
0?
0"
17
0<
0&
0'
0(
1)
#1725
07
1&
#1730
1>
0@
1!
1;
1?
1#
1"
17
1<
0&
1'
#1735
1@
0>
0;
0#
07
1&
#1740
0!
0@
0?
0"
08
17
0<
0%
0&
0'
1(
#1745
07
1&
#1750
1@
1>
1!
1;
1#
17
1<
0&
1'
#1755
0!
0@
0>
0;
0#
07
1&
#1760
18
17
0<
1%
0&
0'
0(
0)
0*
1+
#1765
07
1&
#1770
1>
0@
1!
1;
1?
1#
1"
17
1<
0&
1'
#1775
1@
0>
0;
0#
07
1&
#1780
0!
0@
0?
0"
17
0<
0&
0'
1(
#1785
07
1&
#1790
1>
0@
1!
1;
1?
1#
1"
17
1<
0&
1'
#1795
1@
0>
0;
0#
07
1&
#1800
0!
0@
0?
0"
17
0<
0&
0'
0(
1)
#1805
07
1&
#1810
1>
0@
1!
1;
1?
1#
1"
17
1<
0&
1'
#1815
1@
0>
0;
0#
07
1&
#1820
0!
0@
0?
0"
08
17
0<
0%
0&
0'
1(
#1825
07
1&
#1830
1@
1>
1!
1;
1#
17
1<
0&
1'
#1835
0!
0@
0>
0;
0#
07
1&
#1840
18
17
0<
1%
19
0&
0'
0(
0)
1*
#1845
07
1&
#1850
1>
0@
1!
1;
1?
1#
1"
17
1<
0&
1'
#1855
1@
0>
0;
0#
07
1&
#1860
0!
0@
0?
0"
17
0<
0&
0'
1(
#1865
07
1&
#1870
1>
0@
1!
1;
1?
1#
1"
17
1<
0&
1'
#1875
1@
0>
0;
0#
07
1&
#1880
0!
0@
0?
0"
17
0<
0&
0'
0(
1)
#1885
07
1&
#1890
1>
0@
1!
1;
1?
1#
1"
17
1<
0&
1'
#1895
1@
0>
0;
0#
07
1&
#1900
0!
0@
0?
0"
08
17
0<
0%
0&
0'
1(
#1905
07
1&
#1910
1@
1>
1!
1;
1#
17
1<
0&
1'
#1915
0!
0@
0>
0;
0#
07
1&
#1920
18
17
0<
1%
0&
0'
0(
0)
0*
0+
0,
1-
#1925
07
1&
#1930
1>
0@
1!
1;
1?
1#
1"
17
1<
0&
1'
#1935
1@
0>
0;
0#
07
1&
#1940
0!
0@
0?
0"
17
0<
0&
0'
1(
#1945
07
1&
#1950
1>
0@
1!
1;
1?
1#
1"
17
1<
0&
1'
#1955
1@
0>
0;
0#
07
1&
#1960
0!
0@
0?
0"
17
0<
0&
0'
0(
1)
#1965
07
1&
#1970
1>
0@
1!
1;
1?
1#
1"
17
1<
0&
1'
#1975
1@
0>
0;
0#
07
1&
#1980
0!
0@
0?
0"
08
17
0<
0%
0&
0'
1(
#1985
07
1&
#1990
1@
1>
1!
1;
1#
17
1<
0&
1'
#1995
0!
0@
0>
0;
0#
07
1&
#2000
18
17
0<
1%
09
0&
0'
0(
0)
1*
#2005
07
1&
#2010
1>
0@
1!
1;
1?
1#
1"
17
1<
0&
1'
#2015
1@
0>
0;
0#
07
1&
#2020
0!
0@
0?
0"
17
0<
0&
0'
1(
#2025
07
1&
#2030
1>
0@
1!
1;
1?
1#
1"
17
1<
0&
1'
#2035
1@
0>
0;
0#
07
1&
#2040
0!
0@
0?
0"
17
0<
0&
0'
0(
1)
#2045
07
1&
#2050
1>
0@
1!
1;
1?
1#
1"
17
1<
0&
1'
#2055
1@
0>
0;
0#
07
1&
#2060
0!
0@
0?
0"
08
17
0<
0%
0&
0'
1(
#2065
07
1&
#2070
1@
1>
1!
1;
1#
17
1<
0&
1'
#2075
0!
0@
0>
0;
0#
07
1&
#2080
18
17
0<
1%
0&
0'
0(
0)
0*
1+
#2085
07
1&
#2090
1>
0@
1!
1;
1?
1#
1"
17
1<
0&
1'
#2095
1@
0>
0;
0#
07
1&
#2100
0!
0@
0?
0"
17
0<
0&
0'
1(
#2105
07
1&
#2110
1>
0@
1!
1;
1?
1#
1"
17
1<
0&
1'
#2115
1@
0>
0;
0#
07
1&
#2120
0!
0@
0?
0"
17
0<
0&
0'
0(
1)
#2125
07
1&
#2130
1>
0@
1!
1;
1?
1#
1"
17
1<
0&
1'
#2135
1@
0>
0;
0#
07
1&
#2140
0!
0@
0?
0"
08
17
0<
0%
0&
0'
1(
#2145
07
1&
#2150
1@
1>
1!
1;
1#
17
1<
0&
1'
#2155
0!
0@
0>
0;
0#
07
1&
#2160
18
17
0<
1%
19
0&
0'
0(
0)
1*
#2165
07
1&
#2170
1>
0@
1!
1;
1?
1#
1"
17
1<
0&
1'
#2175
1@
0>
0;
0#
07
1&
#2180
0!
0@
0?
0"
17
0<
0&
0'
1(
#2185
07
1&
#2190
1>
0@
1!
1;
1?
1#
1"
17
1<
0&
1'
#2195
1@
0>
0;
0#
07
1&
#2200
0!
0@
0?
0"
17
0<
0&
0'
0(
1)
#2205
07
1&
#2210
1>
0@
1!
1;
1?
1#
1"
17
1<
0&
1'
#2215
1@
0>
0;
0#
07
1&
#2220
0!
0@
0?
0"
08
17
0<
0%
0&
0'
1(
#2225
07
1&
#2230
1@
1>
1!
1;
1#
17
1<
0&
1'
#2235
0!
0@
0>
0;
0#
07
1&
#2240
0=
18
1:
17
1<
1%
1$
0&
0'
0(
0)
0*
0+
1,
#2245
07
1&
#2250
1!
1;
1#
17
0&
1'
#2255
0!
0;
0#
07
1&
#2260
17
0&
0'
1(
#2265
07
1&
#2270
1!
1;
1#
17
0&
1'
#2275
0!
0;
0#
07
1&
#2280
17
0&
0'
0(
1)
#2285
07
1&
#2290
1!
1;
1#
17
0&
1'
#2295
0!
0;
0#
07
1&
#2300
08
17
0%
0&
0'
1(
#2305
07
1&
#2310
1!
1;
1#
17
0&
1'
#2315
0!
0;
0#
07
1&
#2320
1@
1!
1?
1"
18
1=
17
1%
09
0&
0'
0(
0)
1*
#2325
07
1&
#2330
0@
1>
1;
1#
17
0&
1'
#2335
1@
0>
0;
0#
07
1&
#2340
17
0&
0'
1(
#2345
07
1&
#2350
0@
1>
1;
1#
17
0&
1'
#2355
1@
0>
0;
0#
07
1&
#2360
17
0&
0'
0(
1)
#2365
07
1&
#2370
0@
1>
1;
1#
17
0&
1'
#2375
1@
0>
0;
0#
07
1&
#2380
0!
0@
0?
0"
08
17
0%
0&
0'
1(
#2385
07
1&
#2390
1@
1>
1!
1;
1#
17
0&
1'
#2395
0!
0@
0>
0;
0#
07
1&
#2400
1@
1!
1?
1"
18
17
1%
0&
0'
0(
0)
0*
1+
#2405
07
1&
#2410
0@
1>
1;
1#
17
0&
1'
#2415
1@
0>
0;
0#
07
1&
#2420
17
0&
0'
1(
#2425
07
1&
#2430
0@
1>
1;
1#
17
0&
1'
#2435
1@
0>
0;
0#
07
1&
#2440
17
0&
0'
0(
1)
#2445
07
1&
#2450
0@
1>
1;
1#
17
0&
1'
#2455
1@
0>
0;
0#
07
1&
#2460
0!
0@
0?
0"
08
17
0%
0&
0'
1(
#2465
07
1&
#2470
1@
1>
1!
1;
1#
17
0&
1'
#2475
0!
0@
0>
0;
0#
07
1&
#2480
18
0=
17
1%
19
0&
0'
0(
0)
1*
#2485
07
1&
#2490
1!
1;
1#
17
0&
1'
#2495
0!
0;
0#
07
1&
#2500
17
0&
0'
1(
#2505
07
1&
#2510
1!
1;
1#
17
0&
1'
#2515
0!
0;
0#
07
1&
#2520
17
0&
0'
0(
1)
#2525
07
1&
#2530
1!
1;
1#
17
0&
1'
#2535
0!
0;
0#
07
1&
#2540
08
17
0%
0&
0'
1(
#2545
07
1&
#2550
1!
1;
1#
17
0&
1'
#2555
0!
0;
0#
07
1&
#2560
0<
1=
18
0:
17
1%
0$
0&
0'
0(
0)
0*
0+
0,
0-
0.
#2565
07
1&
